Workbook

Sheet How to use
A1: Planetary Analogue Catalogue: data entry workbook
A2: One row per site on the Sites tab; one row per source on the References tab.
A4: Progress
A5: Sites entered | B5: =COUNTA(Sites!B4:B503)
A6: Complete (ready to review) | B6: =COUNTIF(Sites!BB4:BB503,"Complete")
A7: Verified | B7: =COUNTIF(Sites!AX4:AX503,"Verified")
A8: References logged | B8: =COUNTA(References!A4:A503)
A10: How to fill it in
A11: White cells | B11: Type or pick a value. Columns marked * are required before an entry can be reviewed.
A12: Dropdown columns | B12: Click the cell and choose from the list. Lists live on the Vocabularies tab.
A13: "_other" and hazards columns | B13: Several values from the Vocabularies lists, separated by semicolons, e.g. "Moon; Europa".
A14: Grey columns (Checks) | B14: Calculated automatically. Do not type in them. "Complete" means every required field is filled and the site has at least one reference.
A15: Model entry | B15: Río Tinto (row 4 on Sites) is a good model of a complete entry.
A16: Unknown values | B16: Leave the cell blank. Never guess a number.
A17: Sources | B17: Add each paper to the References tab with the site id, and list which fields it supports.
A18: Ratings | B18: Use the Rating scales tab and fill rating_last_reviewed with the date you checked.
A19: Sensitive sites | B19: Set sensitive_site to Yes and coordinate_precision to "Approximately 10 km" or "Region only".
A20: Review status | B20: Draft while you work → In review when Complete → Verified after a second person checks it.
A22: Note | B22: All 16 sites were researched on 11 October 2026. Every value comes from a source on the References tab, apart from fields marked as judgement on the Research log tab. Hazard and access ratings are proposals: check them, then fill rating_last_reviewed and contributors. Open questions per site are on the Research log tab.
A24: Jump to
A25: =HYPERLINK("#'Site view'!B2","Site view: one site at a time")
A26: =HYPERLINK("#Sites!A2","Sites: Identity")
A27: =HYPERLINK("#Sites!M2","Sites: Analogue")
A28: =HYPERLINK("#Sites!T2","Sites: Geology")
A29: =HYPERLINK("#Sites!X2","Sites: Environment")
A30: =HYPERLINK("#Sites!AI2","Sites: Access")
A31: =HYPERLINK("#Sites!AQ2","Sites: Safety")
A32: =HYPERLINK("#Sites!AU2","Sites: Provenance")
A33: =HYPERLINK("#References!A2","References")
A35: Tip | B35: On the Sites tab, click the small minus buttons above the column letters to fold away sections you are not working on. id and name always stay visible on the left.

Sheet Site view
A1: Site view
A2: Choose a site: | B2: rio-tinto-es | C2: ← click, then use the dropdown
A3: Read-only view of one site. Make changes on the Sites tab (the Edit links jump to the right cell in Excel).
A4: Status | B4: =IFERROR(INDEX(Sites!$BB$4:$BB$503,MATCH($B$2,Sites!$A$4:$A$503,0))&": "&INDEX(Sites!$BA$4:$BA$503,MATCH($B$2,Sites!$A$4:$A$503,0))&" required fields missing, "&INDEX(Sites!$AZ$4:$AZ$503,MATCH($B$2,Sites!$A$4:$A$503,0))&" references","Site not found")
A6: Field | B6: Value | C6: Check | D6: Edit
A7: IDENTITY
A8: id * | B8: =IFERROR(IF(INDEX(Sites!$A$4:$A$503,MATCH($B$2,Sites!$A$4:$A$503,0))="","",INDEX(Sites!$A$4:$A$503,MATCH($B$2,Sites!$A$4:$A$503,0))),"") | C8: =IF(B8="","Required: missing","") | D8: =IFERROR(HYPERLINK("#Sites!A"&(MATCH($B$2,Sites!$A$4:$A$503,0)+3),"Edit"),"")
A9: name * | B9: =IFERROR(IF(INDEX(Sites!$B$4:$B$503,MATCH($B$2,Sites!$A$4:$A$503,0))="","",INDEX(Sites!$B$4:$B$503,MATCH($B$2,Sites!$A$4:$A$503,0))),"") | C9: =IF(B9="","Required: missing","") | D9: =IFERROR(HYPERLINK("#Sites!B"&(MATCH($B$2,Sites!$A$4:$A$503,0)+3),"Edit"),"")
A10: alt_names | B10: =IFERROR(IF(INDEX(Sites!$C$4:$C$503,MATCH($B$2,Sites!$A$4:$A$503,0))="","",INDEX(Sites!$C$4:$C$503,MATCH($B$2,Sites!$A$4:$A$503,0))),"") | C10: =IF(B10="","empty","") | D10: =IFERROR(HYPERLINK("#Sites!C"&(MATCH($B$2,Sites!$A$4:$A$503,0)+3),"Edit"),"")
A11: country * | B11: =IFERROR(IF(INDEX(Sites!$D$4:$D$503,MATCH($B$2,Sites!$A$4:$A$503,0))="","",INDEX(Sites!$D$4:$D$503,MATCH($B$2,Sites!$A$4:$A$503,0))),"") | C11: =IF(B11="","Required: missing","") | D11: =IFERROR(HYPERLINK("#Sites!D"&(MATCH($B$2,Sites!$A$4:$A$503,0)+3),"Edit"),"")
A12: country_code | B12: =IFERROR(IF(INDEX(Sites!$E$4:$E$503,MATCH($B$2,Sites!$A$4:$A$503,0))="","",INDEX(Sites!$E$4:$E$503,MATCH($B$2,Sites!$A$4:$A$503,0))),"") | C12: =IF(B12="","empty","") | D12: =IFERROR(HYPERLINK("#Sites!E"&(MATCH($B$2,Sites!$A$4:$A$503,0)+3),"Edit"),"")
A13: region | B13: =IFERROR(IF(INDEX(Sites!$F$4:$F$503,MATCH($B$2,Sites!$A$4:$A$503,0))="","",INDEX(Sites!$F$4:$F$503,MATCH($B$2,Sites!$A$4:$A$503,0))),"") | C13: =IF(B13="","empty","") | D13: =IFERROR(HYPERLINK("#Sites!F"&(MATCH($B$2,Sites!$A$4:$A$503,0)+3),"Edit"),"")
A14: latitude * | B14: =IFERROR(IF(INDEX(Sites!$G$4:$G$503,MATCH($B$2,Sites!$A$4:$A$503,0))="","",INDEX(Sites!$G$4:$G$503,MATCH($B$2,Sites!$A$4:$A$503,0))),"") | C14: =IF(B14="","Required: missing","") | D14: =IFERROR(HYPERLINK("#Sites!G"&(MATCH($B$2,Sites!$A$4:$A$503,0)+3),"Edit"),"")
A15: longitude * | B15: =IFERROR(IF(INDEX(Sites!$H$4:$H$503,MATCH($B$2,Sites!$A$4:$A$503,0))="","",INDEX(Sites!$H$4:$H$503,MATCH($B$2,Sites!$A$4:$A$503,0))),"") | C15: =IF(B15="","Required: missing","") | D15: =IFERROR(HYPERLINK("#Sites!H"&(MATCH($B$2,Sites!$A$4:$A$503,0)+3),"Edit"),"")
A16: coordinate_precision * | B16: =IFERROR(IF(INDEX(Sites!$I$4:$I$503,MATCH($B$2,Sites!$A$4:$A$503,0))="","",INDEX(Sites!$I$4:$I$503,MATCH($B$2,Sites!$A$4:$A$503,0))),"") | C16: =IF(B16="","Required: missing","") | D16: =IFERROR(HYPERLINK("#Sites!I"&(MATCH($B$2,Sites!$A$4:$A$503,0)+3),"Edit"),"")
A17: sensitive_site * | B17: =IFERROR(IF(INDEX(Sites!$J$4:$J$503,MATCH($B$2,Sites!$A$4:$A$503,0))="","",INDEX(Sites!$J$4:$J$503,MATCH($B$2,Sites!$A$4:$A$503,0))),"") | C17: =IF(B17="","Required: missing","") | D17: =IFERROR(HYPERLINK("#Sites!J"&(MATCH($B$2,Sites!$A$4:$A$503,0)+3),"Edit"),"")
A18: extent_km2 | B18: =IFERROR(IF(INDEX(Sites!$K$4:$K$503,MATCH($B$2,Sites!$A$4:$A$503,0))="","",INDEX(Sites!$K$4:$K$503,MATCH($B$2,Sites!$A$4:$A$503,0))),"") | C18: =IF(B18="","empty","") | D18: =IFERROR(HYPERLINK("#Sites!K"&(MATCH($B$2,Sites!$A$4:$A$503,0)+3),"Edit"),"")
A19: summary * | B19: =IFERROR(IF(INDEX(Sites!$L$4:$L$503,MATCH($B$2,Sites!$A$4:$A$503,0))="","",INDEX(Sites!$L$4:$L$503,MATCH($B$2,Sites!$A$4:$A$503,0))),"") | C19: =IF(B19="","Required: missing","") | D19: =IFERROR(HYPERLINK("#Sites!L"&(MATCH($B$2,Sites!$A$4:$A$503,0)+3),"Edit"),"")
A20: ANALOGUE
A21: analogue_for_primary * | B21: =IFERROR(IF(INDEX(Sites!$M$4:$M$503,MATCH($B$2,Sites!$A$4:$A$503,0))="","",INDEX(Sites!$M$4:$M$503,MATCH($B$2,Sites!$A$4:$A$503,0))),"") | C21: =IF(B21="","Required: missing","") | D21: =IFERROR(HYPERLINK("#Sites!M"&(MATCH($B$2,Sites!$A$4:$A$503,0)+3),"Edit"),"")
A22: analogue_for_other | B22: =IFERROR(IF(INDEX(Sites!$N$4:$N$503,MATCH($B$2,Sites!$A$4:$A$503,0))="","",INDEX(Sites!$N$4:$N$503,MATCH($B$2,Sites!$A$4:$A$503,0))),"") | C22: =IF(B22="","empty","") | D22: =IFERROR(HYPERLINK("#Sites!N"&(MATCH($B$2,Sites!$A$4:$A$503,0)+3),"Edit"),"")
A23: analogue_type_primary * | B23: =IFERROR(IF(INDEX(Sites!$O$4:$O$503,MATCH($B$2,Sites!$A$4:$A$503,0))="","",INDEX(Sites!$O$4:$O$503,MATCH($B$2,Sites!$A$4:$A$503,0))),"") | C23: =IF(B23="","Required: missing","") | D23: =IFERROR(HYPERLINK("#Sites!O"&(MATCH($B$2,Sites!$A$4:$A$503,0)+3),"Edit"),"")
A24: analogue_type_other | B24: =IFERROR(IF(INDEX(Sites!$P$4:$P$503,MATCH($B$2,Sites!$A$4:$A$503,0))="","",INDEX(Sites!$P$4:$P$503,MATCH($B$2,Sites!$A$4:$A$503,0))),"") | C24: =IF(B24="","empty","") | D24: =IFERROR(HYPERLINK("#Sites!P"&(MATCH($B$2,Sites!$A$4:$A$503,0)+3),"Edit"),"")
A25: target_feature | B25: =IFERROR(IF(INDEX(Sites!$Q$4:$Q$503,MATCH($B$2,Sites!$A$4:$A$503,0))="","",INDEX(Sites!$Q$4:$Q$503,MATCH($B$2,Sites!$A$4:$A$503,0))),"") | C25: =IF(B25="","empty","") | D25: =IFERROR(HYPERLINK("#Sites!Q"&(MATCH($B$2,Sites!$A$4:$A$503,0)+3),"Edit"),"")
A26: science_relevance * | B26: =IFERROR(IF(INDEX(Sites!$R$4:$R$503,MATCH($B$2,Sites!$A$4:$A$503,0))="","",INDEX(Sites!$R$4:$R$503,MATCH($B$2,Sites!$A$4:$A$503,0))),"") | C26: =IF(B26="","Required: missing","") | D26: =IFERROR(HYPERLINK("#Sites!R"&(MATCH($B$2,Sites!$A$4:$A$503,0)+3),"Edit"),"")
A27: analogue_limitations | B27: =IFERROR(IF(INDEX(Sites!$S$4:$S$503,MATCH($B$2,Sites!$A$4:$A$503,0))="","",INDEX(Sites!$S$4:$S$503,MATCH($B$2,Sites!$A$4:$A$503,0))),"") | C27: =IF(B27="","empty","") | D27: =IFERROR(HYPERLINK("#Sites!S"&(MATCH($B$2,Sites!$A$4:$A$503,0)+3),"Edit"),"")
A28: GEOLOGY
A29: geological_setting | B29: =IFERROR(IF(INDEX(Sites!$T$4:$T$503,MATCH($B$2,Sites!$A$4:$A$503,0))="","",INDEX(Sites!$T$4:$T$503,MATCH($B$2,Sites!$A$4:$A$503,0))),"") | C29: =IF(B29="","empty","") | D29: =IFERROR(HYPERLINK("#Sites!T"&(MATCH($B$2,Sites!$A$4:$A$503,0)+3),"Edit"),"")
A30: rock_types | B30: =IFERROR(IF(INDEX(Sites!$U$4:$U$503,MATCH($B$2,Sites!$A$4:$A$503,0))="","",INDEX(Sites!$U$4:$U$503,MATCH($B$2,Sites!$A$4:$A$503,0))),"") | C30: =IF(B30="","empty","") | D30: =IFERROR(HYPERLINK("#Sites!U"&(MATCH($B$2,Sites!$A$4:$A$503,0)+3),"Edit"),"")
A31: key_minerals | B31: =IFERROR(IF(INDEX(Sites!$V$4:$V$503,MATCH($B$2,Sites!$A$4:$A$503,0))="","",INDEX(Sites!$V$4:$V$503,MATCH($B$2,Sites!$A$4:$A$503,0))),"") | C31: =IF(B31="","empty","") | D31: =IFERROR(HYPERLINK("#Sites!V"&(MATCH($B$2,Sites!$A$4:$A$503,0)+3),"Edit"),"")
A32: age | B32: =IFERROR(IF(INDEX(Sites!$W$4:$W$503,MATCH($B$2,Sites!$A$4:$A$503,0))="","",INDEX(Sites!$W$4:$W$503,MATCH($B$2,Sites!$A$4:$A$503,0))),"") | C32: =IF(B32="","empty","") | D32: =IFERROR(HYPERLINK("#Sites!W"&(MATCH($B$2,Sites!$A$4:$A$503,0)+3),"Edit"),"")
A33: ENVIRONMENT
A34: environment_type_primary * | B34: =IFERROR(IF(INDEX(Sites!$X$4:$X$503,MATCH($B$2,Sites!$A$4:$A$503,0))="","",INDEX(Sites!$X$4:$X$503,MATCH($B$2,Sites!$A$4:$A$503,0))),"") | C34: =IF(B34="","Required: missing","") | D34: =IFERROR(HYPERLINK("#Sites!X"&(MATCH($B$2,Sites!$A$4:$A$503,0)+3),"Edit"),"")
A35: environment_type_other | B35: =IFERROR(IF(INDEX(Sites!$Y$4:$Y$503,MATCH($B$2,Sites!$A$4:$A$503,0))="","",INDEX(Sites!$Y$4:$Y$503,MATCH($B$2,Sites!$A$4:$A$503,0))),"") | C35: =IF(B35="","empty","") | D35: =IFERROR(HYPERLINK("#Sites!Y"&(MATCH($B$2,Sites!$A$4:$A$503,0)+3),"Edit"),"")
A36: ph_min | B36: =IFERROR(IF(INDEX(Sites!$Z$4:$Z$503,MATCH($B$2,Sites!$A$4:$A$503,0))="","",INDEX(Sites!$Z$4:$Z$503,MATCH($B$2,Sites!$A$4:$A$503,0))),"") | C36: =IF(B36="","empty","") | D36: =IFERROR(HYPERLINK("#Sites!Z"&(MATCH($B$2,Sites!$A$4:$A$503,0)+3),"Edit"),"")
A37: ph_max | B37: =IFERROR(IF(INDEX(Sites!$AA$4:$AA$503,MATCH($B$2,Sites!$A$4:$A$503,0))="","",INDEX(Sites!$AA$4:$AA$503,MATCH($B$2,Sites!$A$4:$A$503,0))),"") | C37: =IF(B37="","empty","") | D37: =IFERROR(HYPERLINK("#Sites!AA"&(MATCH($B$2,Sites!$A$4:$A$503,0)+3),"Edit"),"")
A38: temp_min_c | B38: =IFERROR(IF(INDEX(Sites!$AB$4:$AB$503,MATCH($B$2,Sites!$A$4:$A$503,0))="","",INDEX(Sites!$AB$4:$AB$503,MATCH($B$2,Sites!$A$4:$A$503,0))),"") | C38: =IF(B38="","empty","") | D38: =IFERROR(HYPERLINK("#Sites!AB"&(MATCH($B$2,Sites!$A$4:$A$503,0)+3),"Edit"),"")
A39: temp_max_c | B39: =IFERROR(IF(INDEX(Sites!$AC$4:$AC$503,MATCH($B$2,Sites!$A$4:$A$503,0))="","",INDEX(Sites!$AC$4:$AC$503,MATCH($B$2,Sites!$A$4:$A$503,0))),"") | C39: =IF(B39="","empty","") | D39: =IFERROR(HYPERLINK("#Sites!AC"&(MATCH($B$2,Sites!$A$4:$A$503,0)+3),"Edit"),"")
A40: salinity | B40: =IFERROR(IF(INDEX(Sites!$AD$4:$AD$503,MATCH($B$2,Sites!$A$4:$A$503,0))="","",INDEX(Sites!$AD$4:$AD$503,MATCH($B$2,Sites!$A$4:$A$503,0))),"") | C40: =IF(B40="","empty","") | D40: =IFERROR(HYPERLINK("#Sites!AD"&(MATCH($B$2,Sites!$A$4:$A$503,0)+3),"Edit"),"")
A41: altitude_min_m | B41: =IFERROR(IF(INDEX(Sites!$AE$4:$AE$503,MATCH($B$2,Sites!$A$4:$A$503,0))="","",INDEX(Sites!$AE$4:$AE$503,MATCH($B$2,Sites!$A$4:$A$503,0))),"") | C41: =IF(B41="","empty","") | D41: =IFERROR(HYPERLINK("#Sites!AE"&(MATCH($B$2,Sites!$A$4:$A$503,0)+3),"Edit"),"")
A42: altitude_max_m | B42: =IFERROR(IF(INDEX(Sites!$AF$4:$AF$503,MATCH($B$2,Sites!$A$4:$A$503,0))="","",INDEX(Sites!$AF$4:$AF$503,MATCH($B$2,Sites!$A$4:$A$503,0))),"") | C42: =IF(B42="","empty","") | D42: =IFERROR(HYPERLINK("#Sites!AF"&(MATCH($B$2,Sites!$A$4:$A$503,0)+3),"Edit"),"")
A43: biology_present | B43: =IFERROR(IF(INDEX(Sites!$AG$4:$AG$503,MATCH($B$2,Sites!$A$4:$A$503,0))="","",INDEX(Sites!$AG$4:$AG$503,MATCH($B$2,Sites!$A$4:$A$503,0))),"") | C43: =IF(B43="","empty","") | D43: =IFERROR(HYPERLINK("#Sites!AG"&(MATCH($B$2,Sites!$A$4:$A$503,0)+3),"Edit"),"")
A44: notable_organisms | B44: =IFERROR(IF(INDEX(Sites!$AH$4:$AH$503,MATCH($B$2,Sites!$A$4:$A$503,0))="","",INDEX(Sites!$AH$4:$AH$503,MATCH($B$2,Sites!$A$4:$A$503,0))),"") | C44: =IF(B44="","empty","") | D44: =IFERROR(HYPERLINK("#Sites!AH"&(MATCH($B$2,Sites!$A$4:$A$503,0)+3),"Edit"),"")
A45: ACCESS
A46: access_level * | B46: =IFERROR(IF(INDEX(Sites!$AI$4:$AI$503,MATCH($B$2,Sites!$A$4:$A$503,0))="","",INDEX(Sites!$AI$4:$AI$503,MATCH($B$2,Sites!$A$4:$A$503,0))),"") | C46: =IF(B46="","Required: missing","") | D46: =IFERROR(HYPERLINK("#Sites!AI"&(MATCH($B$2,Sites!$A$4:$A$503,0)+3),"Edit"),"")
A47: permits_required * | B47: =IFERROR(IF(INDEX(Sites!$AJ$4:$AJ$503,MATCH($B$2,Sites!$A$4:$A$503,0))="","",INDEX(Sites!$AJ$4:$AJ$503,MATCH($B$2,Sites!$A$4:$A$503,0))),"") | C47: =IF(B47="","Required: missing","") | D47: =IFERROR(HYPERLINK("#Sites!AJ"&(MATCH($B$2,Sites!$A$4:$A$503,0)+3),"Edit"),"")
A48: permit_authority | B48: =IFERROR(IF(INDEX(Sites!$AK$4:$AK$503,MATCH($B$2,Sites!$A$4:$A$503,0))="","",INDEX(Sites!$AK$4:$AK$503,MATCH($B$2,Sites!$A$4:$A$503,0))),"") | C48: =IF(B48="","empty","") | D48: =IFERROR(HYPERLINK("#Sites!AK"&(MATCH($B$2,Sites!$A$4:$A$503,0)+3),"Edit"),"")
A49: land_status | B49: =IFERROR(IF(INDEX(Sites!$AL$4:$AL$503,MATCH($B$2,Sites!$A$4:$A$503,0))="","",INDEX(Sites!$AL$4:$AL$503,MATCH($B$2,Sites!$A$4:$A$503,0))),"") | C49: =IF(B49="","empty","") | D49: =IFERROR(HYPERLINK("#Sites!AL"&(MATCH($B$2,Sites!$A$4:$A$503,0)+3),"Edit"),"")
A50: nearest_town | B50: =IFERROR(IF(INDEX(Sites!$AM$4:$AM$503,MATCH($B$2,Sites!$A$4:$A$503,0))="","",INDEX(Sites!$AM$4:$AM$503,MATCH($B$2,Sites!$A$4:$A$503,0))),"") | C50: =IF(B50="","empty","") | D50: =IFERROR(HYPERLINK("#Sites!AM"&(MATCH($B$2,Sites!$A$4:$A$503,0)+3),"Edit"),"")
A51: best_season | B51: =IFERROR(IF(INDEX(Sites!$AN$4:$AN$503,MATCH($B$2,Sites!$A$4:$A$503,0))="","",INDEX(Sites!$AN$4:$AN$503,MATCH($B$2,Sites!$A$4:$A$503,0))),"") | C51: =IF(B51="","empty","") | D51: =IFERROR(HYPERLINK("#Sites!AN"&(MATCH($B$2,Sites!$A$4:$A$503,0)+3),"Edit"),"")
A52: transport_notes | B52: =IFERROR(IF(INDEX(Sites!$AO$4:$AO$503,MATCH($B$2,Sites!$A$4:$A$503,0))="","",INDEX(Sites!$AO$4:$AO$503,MATCH($B$2,Sites!$A$4:$A$503,0))),"") | C52: =IF(B52="","empty","") | D52: =IFERROR(HYPERLINK("#Sites!AO"&(MATCH($B$2,Sites!$A$4:$A$503,0)+3),"Edit"),"")
A53: sampling_rules | B53: =IFERROR(IF(INDEX(Sites!$AP$4:$AP$503,MATCH($B$2,Sites!$A$4:$A$503,0))="","",INDEX(Sites!$AP$4:$AP$503,MATCH($B$2,Sites!$A$4:$A$503,0))),"") | C53: =IF(B53="","empty","") | D53: =IFERROR(HYPERLINK("#Sites!AP"&(MATCH($B$2,Sites!$A$4:$A$503,0)+3),"Edit"),"")
A54: SAFETY
A55: hazard_rating * | B55: =IFERROR(IF(INDEX(Sites!$AQ$4:$AQ$503,MATCH($B$2,Sites!$A$4:$A$503,0))="","",INDEX(Sites!$AQ$4:$AQ$503,MATCH($B$2,Sites!$A$4:$A$503,0))),"") | C55: =IF(B55="","Required: missing","") | D55: =IFERROR(HYPERLINK("#Sites!AQ"&(MATCH($B$2,Sites!$A$4:$A$503,0)+3),"Edit"),"")
A56: hazards * | B56: =IFERROR(IF(INDEX(Sites!$AR$4:$AR$503,MATCH($B$2,Sites!$A$4:$A$503,0))="","",INDEX(Sites!$AR$4:$AR$503,MATCH($B$2,Sites!$A$4:$A$503,0))),"") | C56: =IF(B56="","Required: missing","") | D56: =IFERROR(HYPERLINK("#Sites!AR"&(MATCH($B$2,Sites!$A$4:$A$503,0)+3),"Edit"),"")
A57: safety_notes | B57: =IFERROR(IF(INDEX(Sites!$AS$4:$AS$503,MATCH($B$2,Sites!$A$4:$A$503,0))="","",INDEX(Sites!$AS$4:$AS$503,MATCH($B$2,Sites!$A$4:$A$503,0))),"") | C57: =IF(B57="","empty","") | D57: =IFERROR(HYPERLINK("#Sites!AS"&(MATCH($B$2,Sites!$A$4:$A$503,0)+3),"Edit"),"")
A58: rating_last_reviewed * | B58: =IFERROR(IF(INDEX(Sites!$AT$4:$AT$503,MATCH($B$2,Sites!$A$4:$A$503,0))="","",INDEX(Sites!$AT$4:$AT$503,MATCH($B$2,Sites!$A$4:$A$503,0))),"") | C58: =IF(B58="","Required: missing","") | D58: =IFERROR(HYPERLINK("#Sites!AT"&(MATCH($B$2,Sites!$A$4:$A$503,0)+3),"Edit"),"")
A59: PROVENANCE
A60: contributors * | B60: =IFERROR(IF(INDEX(Sites!$AU$4:$AU$503,MATCH($B$2,Sites!$A$4:$A$503,0))="","",INDEX(Sites!$AU$4:$AU$503,MATCH($B$2,Sites!$A$4:$A$503,0))),"") | C60: =IF(B60="","Required: missing","") | D60: =IFERROR(HYPERLINK("#Sites!AU"&(MATCH($B$2,Sites!$A$4:$A$503,0)+3),"Edit"),"")
A61: date_added * | B61: =IFERROR(IF(INDEX(Sites!$AV$4:$AV$503,MATCH($B$2,Sites!$A$4:$A$503,0))="","",INDEX(Sites!$AV$4:$AV$503,MATCH($B$2,Sites!$A$4:$A$503,0))),"") | C61: =IF(B61="","Required: missing","") | D61: =IFERROR(HYPERLINK("#Sites!AV"&(MATCH($B$2,Sites!$A$4:$A$503,0)+3),"Edit"),"")
A62: last_verified | B62: =IFERROR(IF(INDEX(Sites!$AW$4:$AW$503,MATCH($B$2,Sites!$A$4:$A$503,0))="","",INDEX(Sites!$AW$4:$AW$503,MATCH($B$2,Sites!$A$4:$A$503,0))),"") | C62: =IF(B62="","empty","") | D62: =IFERROR(HYPERLINK("#Sites!AW"&(MATCH($B$2,Sites!$A$4:$A$503,0)+3),"Edit"),"")
A63: review_status * | B63: =IFERROR(IF(INDEX(Sites!$AX$4:$AX$503,MATCH($B$2,Sites!$A$4:$A$503,0))="","",INDEX(Sites!$AX$4:$AX$503,MATCH($B$2,Sites!$A$4:$A$503,0))),"") | C63: =IF(B63="","Required: missing","") | D63: =IFERROR(HYPERLINK("#Sites!AX"&(MATCH($B$2,Sites!$A$4:$A$503,0)+3),"Edit"),"")
A64: notes_for_reviewer | B64: =IFERROR(IF(INDEX(Sites!$AY$4:$AY$503,MATCH($B$2,Sites!$A$4:$A$503,0))="","",INDEX(Sites!$AY$4:$AY$503,MATCH($B$2,Sites!$A$4:$A$503,0))),"") | C64: =IF(B64="","empty","") | D64: =IFERROR(HYPERLINK("#Sites!AY"&(MATCH($B$2,Sites!$A$4:$A$503,0)+3),"Edit"),"")

Sheet Sites
A1: IDENTITY | M1: ANALOGUE | T1: GEOLOGY | X1: ENVIRONMENT | AI1: ACCESS | AQ1: SAFETY | AU1: PROVENANCE | AZ1: CHECKS (AUTOMATIC)
A2: id * | B2: name * | C2: alt_names | D2: country * | E2: country_code | F2: region | G2: latitude * | H2: longitude * | I2: coordinate_precision * | J2: sensitive_site * | K2: extent_km2 | L2: summary * | M2: analogue_for_primary * | N2: analogue_for_other | O2: analogue_type_primary * | P2: analogue_type_other | Q2: target_feature | R2: science_relevance * | S2: analogue_limitations | T2: geological_setting | U2: rock_types | V2: key_minerals | W2: age | X2: environment_type_primary * | Y2: environment_type_other | Z2: ph_min | AA2: ph_max | AB2: temp_min_c | AC2: temp_max_c | AD2: salinity | AE2: altitude_min_m | AF2: altitude_max_m | AG2: biology_present | AH2: notable_organisms | AI2: access_level * | AJ2: permits_required * | AK2: permit_authority | AL2: land_status | AM2: nearest_town | AN2: best_season | AO2: transport_notes | AP2: sampling_rules | AQ2: hazard_rating * | AR2: hazards * | AS2: safety_notes | AT2: rating_last_reviewed * | AU2: contributors * | AV2: date_added * | AW2: last_verified | AX2: review_status * | AY2: notes_for_reviewer | AZ2: reference_count | BA2: required_missing | BB2: entry_check
A3: Short unique slug: site-name-countrycode | B3: Common name of the site | C3: Other names; separate with ; | D3: Country or "International waters" | E3: ISO 3166 two-letter code | F3: State, province or area | G3: Decimal degrees, WGS84 (south is minus) | H3: Decimal degrees, WGS84 (west is minus) | I3: How precisely to publish the location | J3: Fragile, protected or Indigenous land? | K3: Approximate area in km² | L3: One line, under 300 characters | M3: Main body it is an analogue for | N3: Other bodies; separate with ; | O3: Main kind of analogue | P3: Other kinds; separate with ; | Q3: Planetary feature it is compared with | R3: Why it is a good analogue | S3: Where the comparison breaks down | T3: Main setting | U3: Separate with ; | V3: mindat.org names; separate with ; | W3: Age of rocks or features | X3: Main environment | Y3: Others; separate with ; | Z3: pH, 0 to 14 | AA3: pH, 0 to 14 | AB3: Temperature, °C | AC3: Temperature, °C | AD3: Value with units, or a description | AE3: Metres above sea level | AF3: Metres above sea level | AG3: Is life present at the site? | AH3: Key organisms or communities | AI3: 1 to 5; see Rating scales tab | AJ3: Are permits needed? | AK3: Who issues them; add a link | AL3: Who owns or manages the land | AN3: When to visit | AO3: Roads, 4x4, boat, hike | AP3: What may be sampled, under which permit | AQ3: 1 to 5; see Rating scales tab | AR3: From the hazards list; separate with ; | AS3: Precautions visitors should take | AT3: Date ratings were checked (YYYY-MM-DD) | AU3: Names or ORCIDs; separate with ; | AV3: YYYY-MM-DD | AW3: YYYY-MM-DD | AX3: Where the entry is in review | AY3: Anything still to check | AZ3: Rows for this id on the References tab | BA3: Required fields still empty | BB3: Complete = all required fields + 1 reference
A4: rio-tinto-es | B4: Río Tinto | C4: Rio Tinto; Tinto River | D4: Spain | E4: ES | F4: Huelva, Andalusia | G4: 37.21 | H4: -6.938 | I4: Approximately 10 km | J4: No | K4: 169.57 | L4: Highly acidic, iron-rich river (mean pH 2.3) rising at Peña de Hierro in the Iberian Pyrite Belt and reaching the Atlantic at Huelva. Its ferric sulphates and iron oxides, including jarosite and hematite, make it a classic analogue for Meridiani Planum, Mars. | M4: Mars | N4: Europa | O4: Mineralogical | P4: Geochemical; Habitability / biological | Q4: Meridiani Planum sulphate- and hematite-bearing outcrops (jarosite, hematite) | R4: Río Tinto precipitates jarosite, schwertmannite, goethite and hematite from acidic, iron-rich water, comparable to the jarosite and hematite identified at Meridiani Planum by Mössbauer spectroscopy. Its acidity is generated by chemolithotrophic micro-organisms oxidising subsurface pyrite, making it a model for iron- and sulphur-based habitability on Mars. | S4: Meridiani sediments formed in an arid aeolian and aqueous setting, whereas Tinto sediments form in seasonally arid stream beds; Tinto acidity comes from pyrite oxidation, which is not the only possible source of acidic fluids on Mars; ferric sulphates do not persist in the Tinto rock record, unlike Meridiani; the basin has more than 5,000 years of mining history. | T4: Hydrothermal / ore deposit | U4: Massive sulphide (pyrite) ore bodies; gossans; ferruginous river terraces | V4: Jarosite; Hydroniumjarosite; Schwertmannite; Copiapite; Coquimbite; Gypsum; Goethite; Hematite; Pyrite; Siderite | W4: Iberian Pyrite Belt formed during the Hercynian orogeny; gossans older than 6 Ma; oldest river terrace dated to 2.1 Ma | X4: Acidic | Y4: Iron-rich; Sulphur-rich | Z4: 2 | AA4: 2.5 | AG4: Yes | AH4: Acidithiobacillus; Leptospirillum; Acidiphilium; Chlamydomonas; Dunaliella; Chlorella; Klebsormidium; Cyanidium; Euglena; pennate diatoms; Methanosaeta concilii (sediments) | AI4: 2 | AJ4: Varies | AK4: Junta de Andalucía (Consejería de Medio Ambiente), managing authority of the Paisaje Protegido de Río Tinto | AL4: Protected area / national park | AM4: Minas de Riotinto; Nerva | AP4: Protected landscape (Decree 558/2004): access to publicly owned land only via designated, signposted places; the environment authority may restrict zones for research or conservation; aggregate extraction and actions altering the river's water character are prohibited; no specific sampling rules are set out in the decree. | AQ4: 2 | AR4: Acidic or caustic water; Old mine workings | AS4: River water is around pH 2; avoid skin and eye contact and use gloves and eye protection when sampling. The basin contains extensive historical and active mine workings (copper production restarted in 2016). | AV4: 46306 | AX4: Draft | AY4: Ratings are PROPOSALS by Claude: check against Rating scales, then fill rating_last_reviewed. Open issues: see Research log tab. | AZ4: =IF($B4="","",COUNTIF(References!$A$4:$A$503,$A4)) | BA4: =IF($B4="","",(LEN(A4)=0)+(LEN(B4)=0)+(LEN(D4)=0)+(LEN(G4)=0)+(LEN(H4)=0)+(LEN(I4)=0)+(LEN(J4)=0)+(LEN(L4)=0)+(LEN(M4)=0)+(LEN(O4)=0)+(LEN(R4)=0)+(LEN(X4)=0)+(LEN(AI4)=0)+(LEN(AJ4)=0)+(LEN(AQ4)=0)+(LEN(AR4)=0)+(LEN(AT4)=0)+(LEN(AU4)=0)+(LEN(AV4)=0)+(LEN(AX4)=0)) | BB4: =IF($B4="","",IF(AND(BA4=0,AZ4>=1),"Complete","Incomplete"))
A5: atacama-yungay-cl | B5: Atacama Desert – Yungay area | C5: Yungay hyperarid site | D5: Chile | E5: CL | F5: Antofagasta Region, hyperarid core of the Atacama Desert | G5: -24.1 | H5: -70.01 | I5: Approximately 10 km | J5: No | L5: Hyperarid core of the Atacama Desert near Yungay, Chile. Its saline soils, rich in nitrates, sulphates and perchlorates and very poor in organics, hold extremely sparse microbial life. The site is a classic Mars soil analogue first proposed in 2003. | M5: Mars | O5: Habitability / biological | P5: Geochemical | Q5: Hyperarid, oxidising, nitrate- and perchlorate-bearing soils with trace organics (dry limit of microbial life) | R5: Navarro-González et al. (2003) found Mars-like soils at Yungay: trace organics, very few culturable bacteria, no recoverable DNA, and non-biological decomposition of organics in Viking-style labelled-release experiments. Later work uses the site as an analogue for an incomplete nitrogen cycle on Mars and for the effect of rare floods on dry-adapted ecosystems. | V5: Halite; Nitratine | X5: Hyperarid | Y5: Evaporite | AD5: Highly saline soils enriched in nitrates, sulphates and perchlorates; halite and sodium nitrate identified by XRD in post-rain lagoons | AG5: Yes | AH5: Halomonas yungayensis (new species described from post-2017-rain lagoons); Halomonas, Marinimicrobium, Marinobacter, Acinetobacter dominate post-rain soils | AI5: 2 | AQ5: 2 | AV5: 46306 | AX5: Draft | AY5: Ratings are PROPOSALS by Claude: check against Rating scales, then fill rating_last_reviewed. Open issues: see Research log tab. | AZ5: =IF($B5="","",COUNTIF(References!$A$4:$A$503,$A5)) | BA5: =IF($B5="","",(LEN(A5)=0)+(LEN(B5)=0)+(LEN(D5)=0)+(LEN(G5)=0)+(LEN(H5)=0)+(LEN(I5)=0)+(LEN(J5)=0)+(LEN(L5)=0)+(LEN(M5)=0)+(LEN(O5)=0)+(LEN(R5)=0)+(LEN(X5)=0)+(LEN(AI5)=0)+(LEN(AJ5)=0)+(LEN(AQ5)=0)+(LEN(AR5)=0)+(LEN(AT5)=0)+(LEN(AU5)=0)+(LEN(AV5)=0)+(LEN(AX5)=0)) | BB5: =IF($B5="","",IF(AND(BA5=0,AZ5>=1),"Complete","Incomplete"))
A6: dallol-et | B6: Dallol | C6: Dallol dome; Dallol hydrothermal system | D6: Ethiopia | E6: ET | F6: Danakil Depression, Afar Region | G6: 14.242 | H6: 40.3 | I6: Approximately 1 km | J6: No | L6: Protovolcanic dome in the Danakil Depression, Ethiopia, where basaltic magma heats evaporites. The result is anoxic, hypersaline, iron-rich brines (pH down to -1.7, up to about 108 °C). The site is used to study the limits of life and iron mineralogy relevant to Mars. | M6: Mars | N6: Early Earth | O6: Geochemical | P6: Habitability / biological; Mineralogical | Q6: Hyperacidic, hypersaline, iron-rich hydrothermal springs and brine pools precipitating jarosite-group minerals, akaganeite and hematite over halite | R6: Kotopoulou et al. (2019) describe Dallol as a Martian analogue where inorganic iron oxidation precipitates jarosite and akaganeite, minerals also identified on Mars. Belilla et al. (2019) found two physicochemical barriers to life where liquid water is present: chaotropic Mg/Ca brines, and pH around 0 combined with NaCl saturation. Diverse ultrasmall archaea occur only outside these conditions. | T6: Volcanic | U6: Evaporites (halite-dominated salt deposits, potash) over basaltic magma | V6: Halite; Jarosite; Akaganeite; Hematite; Gypsum; Sylvite; Carnallite; Sulphur; Goethite; Anhydrite | W6: Dallol volcano formed in phreatic eruptions in 1926. The last activity, possibly degassing, was in January 2011. The age of the hydrothermal system is unknown. | X6: Hot spring / hydrothermal | Y6: Acidic; Hypersaline; Iron-rich; Evaporite | Z6: -1.7 | AA6: 2.5 | AB6: 32 | AC6: 108.4 | AD6: Hypersaline: brines supersaturated in NaCl, with up to 150 g/L iron (mean about 22.5 g/L in spring brines). Mg/Ca-dominated chaotropic brines also occur. | AE6: -120 | AF6: -60 | AG6: Yes | AH6: Highly diverse ultrasmall archaea (including Nanohaloarchaea) in the surrounding salt plains and less extreme brines. No life was detected in the hyperacidic, hypersaline dome ponds. | AI6: 4 | AL6: Unknown | AQ6: 4 | AR6: Extreme heat; Toxic gas; Acidic or caustic water; Political instability | AS6: The UK FCDO (updated 7 October 2026) advises against all but essential travel to Afar, and against all travel within 20 km of the Eritrean border and within 50 km of Tigray. It reports renewed clashes in parts of Afar. Foreign nationals currently cannot fly into Afar airports, and medical facilities outside Addis Ababa are extremely limited. Fumaroles emit CO2, H2S and SO2. Brines reach about 108 °C and pH below 0. | AV6: 46306 | AX6: Draft | AY6: Ratings are PROPOSALS by Claude: check against Rating scales, then fill rating_last_reviewed. geological_setting also: Evaporite basin; Hydrothermal / ore deposit Open issues: see Research log tab. | AZ6: =IF($B6="","",COUNTIF(References!$A$4:$A$503,$A6)) | BA6: =IF($B6="","",(LEN(A6)=0)+(LEN(B6)=0)+(LEN(D6)=0)+(LEN(G6)=0)+(LEN(H6)=0)+(LEN(I6)=0)+(LEN(J6)=0)+(LEN(L6)=0)+(LEN(M6)=0)+(LEN(O6)=0)+(LEN(R6)=0)+(LEN(X6)=0)+(LEN(AI6)=0)+(LEN(AJ6)=0)+(LEN(AQ6)=0)+(LEN(AR6)=0)+(LEN(AT6)=0)+(LEN(AU6)=0)+(LEN(AV6)=0)+(LEN(AX6)=0)) | BB6: =IF($B6="","",IF(AND(BA6=0,AZ6>=1),"Complete","Incomplete"))
A7: mcmurdo-dry-valleys-aq | B7: McMurdo Dry Valleys | C7: Dry Valleys; McMurdo Dry Valleys ASMA No. 2 | D7: Antarctica | E7: AQ | F7: Victoria Land, East Antarctica (between the East Antarctic Ice Sheet and McMurdo Sound/Ross Sea) | G7: -77 | H7: 162 | I7: Region only | J7: Yes | K7: 4500 | L7: About 4,500 km2 of mostly ice-free valleys in Victoria Land: a cold, extremely arid, windy polar desert of valleys, ice-covered lakes and permafrost soils. A long-standing Mars analogue (used by NASA since Viking) and home of cryptoendolithic microbial communities living inside rocks. | M7: Mars | N7: Early Earth | O7: Habitability / biological | P7: Geological / geomorphological; Cryospheric | Q7: Cryptoendolithic communities in porous rocks; cold-desert soils, permafrost and ice-covered lakes | R7: The cold, extremely arid and windy climate is regarded as an analogue for contemporary Mars and ancient Earth. Cryptoendolithic lichens and microbes survive by growing between the crystals of porous rocks, a model for where life might persist near the surface of Mars. Microclimate zonation and geomorphic processes are used to interpret Martian landforms and climate change. | S7: Unlike Mars, the valleys have an oxygen-rich atmosphere, liquid water in summer (meltwater streams and lakes) and annual precipitation of around 100 mm; endolithic life is therefore not directly comparable with present-day Martian conditions. | T7: Glacial | U7: Granite; gneiss; marble and calc-schist (Asgard Formation, Skelton Group); granitoid plutons and dykes (Granite Harbour Intrusives); Beacon Supergroup sedimentary rocks; Ferrar Dolerite; McMurdo Volcanic Group basalt; glacial till | W7: Basement metamorphic and intrusive rocks overlain by the Beacon Supergroup intruded by Jurassic Ferrar Dolerite; McMurdo Volcanic Group basalts 2.1–4.4 Ma | X7: Polar desert | Y7: Permafrost; Hypersaline | AB7: -65.7 | AC7: 12 | AD7: Mostly fresh to saline ice-covered lakes; Lake Vida saline; Don Juan Pond the most saline water body | AG7: Yes | AH7: Cryptoendolithic lichens and photosynthetic bacteria inside porous rocks; microbial mats; cryoconite communities; anaerobic iron- and sulphur-based bacteria beneath Taylor Glacier | AI7: 5 | AJ7: Yes | AK7: Competent national authority of the expedition's Antarctic Treaty Party (e.g. UK: FCDO Polar Regions Department), under the Protocol on Environmental Protection; separate permits to enter ASPAs 123, 131, 138 and 154 inside the ASMA | AL7: Protected area / national park | AM7: Ross Island (helicopter departure point) | AO7: Access normally by helicopter from Ross Island, or over sea ice via New Harbor or Marble Point. Helicopters should use designated pads; overflight restrictions over ASPAs 123, 131 and 154. Vehicles restricted to lake ice or existing tracks unless specifically authorised. | AP7: Specimens (including rocks and fossils) only for scientific or associated educational purposes; collect only the minimum endolithic community sample needed for analysis; taking of native flora/fauna needs an Annex II permit; avoid trampling microbial mats (e.g. walk only on rocks at Boulder Pavement); follow ASMA zoning (Facilities, Tourism zone near Canada Glacier, Special Features). | AQ7: 4 | AR7: Extreme cold; Remoteness / no phone signal | AS7: Strong katabatic winds: secure all equipment and supplies. Take extreme care with vehicles on lake ice to avoid rollover or breaking through. Spill kits and secondary containment required for fuel and chemicals. Record air temperatures range from 12.0 °C to −65.7 °C. | AV7: 46306 | AX7: Draft | AY7: Ratings are PROPOSALS by Claude: check against Rating scales, then fill rating_last_reviewed. Open issues: see Research log tab. | AZ7: =IF($B7="","",COUNTIF(References!$A$4:$A$503,$A7)) | BA7: =IF($B7="","",(LEN(A7)=0)+(LEN(B7)=0)+(LEN(D7)=0)+(LEN(G7)=0)+(LEN(H7)=0)+(LEN(I7)=0)+(LEN(J7)=0)+(LEN(L7)=0)+(LEN(M7)=0)+(LEN(O7)=0)+(LEN(R7)=0)+(LEN(X7)=0)+(LEN(AI7)=0)+(LEN(AJ7)=0)+(LEN(AQ7)=0)+(LEN(AR7)=0)+(LEN(AT7)=0)+(LEN(AU7)=0)+(LEN(AV7)=0)+(LEN(AX7)=0)) | BB7: =IF($B7="","",IF(AND(BA7=0,AZ7>=1),"Complete","Incomplete"))
A8: haughton-crater-ca | B8: Haughton impact structure | C8: Haughton crater; Haughton Dome | D8: Canada | E8: CA | F8: Devon Island, Nunavut | G8: 75.383 | H8: -89.667 | I8: Approximately 10 km | J8: Yes | L8: Well-preserved c. 23 km impact structure on Devon Island in the Canadian High Arctic polar desert. It is home to the Haughton-Mars Project research station and is used for Mars and Moon geology, astrobiology and exploration analogue work. | M8: Mars | N8: Moon | O8: Impact | P8: Geological / geomorphological; Habitability / biological; Operational (instrument, rover or crew testing) | Q8: Crater-fill impact melt breccias; post-impact hydrothermal deposits; glacial and periglacial landforms and canyons (e.g. Astronaut Canyon, compared with a tributary of Ius Chasma on Mars) | R8: One of the best-preserved impact structures on Earth, in a cold, dry polar desert where weathering is slow. Heat from the impact melts drove a hydrothermal system that may have been a warm, wet microbial habitat, which makes it a model for impact-generated habitats on Mars. The site is also used to test habitats, spacesuits, rovers and drones for Moon and Mars missions. | T8: Impact | U8: Impact melt breccia; shale; siltstone; gneiss (basement); lacustrine mudstone and siltstone (Haughton Formation) | V8: Calcite; Anhydrite | W8: Impact c. 31 Ma (40Ar/39Ar weighted mean 31.04 ± 0.37 Ma; U-Pb lower intercept 31.8 ± 1.7 Ma; Erickson et al. 2021). An earlier estimate of c. 39 Ma (Osinski et al. 2005) is now superseded. Haughton Formation lake sediments are Miocene. | X8: Impact structure | Y8: Polar desert; Permafrost | AG8: Yes | AI8: 4 | AJ8: Yes | AK8: Nunavut Research Institute (Scientific Research Licence); Qikiqtani Inuit Association (Access to Inuit Owned Lands Permit); Nunavut Impact Review Board (screening of land-based research); Crown-Indigenous Relations and Northern Affairs Canada (Territorial Land Use Permit on Crown land); Mars Institute (written permission for non-Nunavut visitors to the HMP leased land) | AL8: Indigenous or community land | AN8: Summer (HMP field campaigns have run every summer since 1997) | AO8: No road access. The HMP Research Station has a c. 200 m dirt airstrip, and ATVs are used locally. The Mars Institute asks visitors to contact it first to confirm the airstrip is clear, find out where experiments are running and learn the ATV trail routes. | AP8: A NRI Scientific Research Licence is needed for natural and physical science. Land-based research is screened by the NIRB. Archaeological and palaeontological sites need permits from GN Culture and Heritage. Access to Inuit Owned Land needs a permit from the designated Inuit organisation. | AQ8: 4 | AR8: Extreme cold; Dangerous wildlife; Remoteness / no phone signal | AS8: Polar bears do reach field camps on Devon Island. Western University teams use electrified bear fencing around sleeping tents, set about a football field's distance from food, lab and toilet tents. They ban food and scented products from sleeping tents and carry shotguns and bear bangers. Report polar bear sightings to the local Government of Nunavut wildlife office. | AV8: 46306 | AX8: Draft | AY8: Ratings are PROPOSALS by Claude: check against Rating scales, then fill rating_last_reviewed. land_status also: Research station Open issues: see Research log tab. | AZ8: =IF($B8="","",COUNTIF(References!$A$4:$A$503,$A8)) | BA8: =IF($B8="","",(LEN(A8)=0)+(LEN(B8)=0)+(LEN(D8)=0)+(LEN(G8)=0)+(LEN(H8)=0)+(LEN(I8)=0)+(LEN(J8)=0)+(LEN(L8)=0)+(LEN(M8)=0)+(LEN(O8)=0)+(LEN(R8)=0)+(LEN(X8)=0)+(LEN(AI8)=0)+(LEN(AJ8)=0)+(LEN(AQ8)=0)+(LEN(AR8)=0)+(LEN(AT8)=0)+(LEN(AU8)=0)+(LEN(AV8)=0)+(LEN(AX8)=0)) | BB8: =IF($B8="","",IF(AND(BA8=0,AZ8>=1),"Complete","Incomplete"))
A9: iceland-volcanic-fields-is | B9: Iceland volcanic fields (Holuhraun and Krafla) | C9: Holuhraun lava field; Krafla caldera | D9: Iceland | E9: IS | F9: North-east Iceland: Highlands north of Vatnajökull (Holuhraun) and Mývatn area (Krafla) | G9: 64.85 | H9: -16.83 | I9: Region only | J9: No | K9: 85 | L9: Young basaltic fissure-fed lava fields in Iceland's rift zone: the 2014–15 Holuhraun flow-field north of Vatnajökull and the Krafla caldera near Mývatn. They are used as analogues for young Martian volcanic terrains and for aqueous alteration of basalt. | M9: Mars | O9: Volcanic | P9: Geological / geomorphological; Mineralogical | Q9: The 2014–15 Holuhraun fissure-fed lava flow-field ('transitional' lavas, polygonal terrain, lava–water interaction); altered Icelandic basalts with smectite clays and other hydrous silicates; the Krafla caldera (c. 10 km) and its 90 km fissure zone | R9: Holuhraun is a large-volume, fissure-fed eruption used as an analogue for Elysium Planitia, the youngest volcanic terrain on Mars. Lava morphologies and fissure systems there point to similar extensional settings. Water-altered Icelandic basalts are used to test how well spectroscopic and XRD methods detect clay minerals, to help interpret Noachian aqueous environments on Mars. | T9: Volcanic | U9: Basalt; rhyolite (magma found at c. 2.1 km depth at Krafla) | W9: Holuhraun lava erupted 29 August 2014 – 27 February 2015; Krafla Fires eruptions 1975–1984 | X9: Lava field / lava tube | Y9: Hot spring / hydrothermal | AI9: 3 | AK9: Nature Conservation Agency of Iceland (Vatnajökull National Park) | AL9: Protected area / national park | AN9: Summer. Highland roads usually open between late May and mid-July, depending on snow. | AO9: Holuhraun is in the Askja & Herðubreiðarlindir area of Vatnajökull National Park and is reached by seasonal highland roads. Roads in conservation areas may stay closed until the area can take visitors even when the road is clear. Check road.is or call 1777 for current conditions. Krafla is in the Mývatn area of north Iceland. | AP9: Visitors may only go on the waymarked trail from the Holuhraun parking lot, and the thin lava crust is easily damaged. The park lists permits but the page gives no details, so ask the park office about research sampling. | AQ9: 3 | AR9: Unstable ground; Volcanic activity | AS9: The Holuhraun lava is extremely rugged and difficult terrain, with a thin, fragile crust, so keep to the marked trail. Holuhraun was fed from the Bárðarbunga system, about 41 km to the south-west. | AV9: 46306 | AX9: Draft | AY9: Ratings are PROPOSALS by Claude: check against Rating scales, then fill rating_last_reviewed. geological_setting also: Hydrothermal / ore deposit Open issues: see Research log tab. | AZ9: =IF($B9="","",COUNTIF(References!$A$4:$A$503,$A9)) | BA9: =IF($B9="","",(LEN(A9)=0)+(LEN(B9)=0)+(LEN(D9)=0)+(LEN(G9)=0)+(LEN(H9)=0)+(LEN(I9)=0)+(LEN(J9)=0)+(LEN(L9)=0)+(LEN(M9)=0)+(LEN(O9)=0)+(LEN(R9)=0)+(LEN(X9)=0)+(LEN(AI9)=0)+(LEN(AJ9)=0)+(LEN(AQ9)=0)+(LEN(AR9)=0)+(LEN(AT9)=0)+(LEN(AU9)=0)+(LEN(AV9)=0)+(LEN(AX9)=0)) | BB9: =IF($B9="","",IF(AND(BA9=0,AZ9>=1),"Complete","Incomplete"))
A10: pilbara-strelley-pool-au | B10: Pilbara Craton: Strelley Pool and Dresser formations | C10: Strelley Pool Chert; Trendall locality; North Pole Dome; Dresser Mine | D10: Australia | E10: AU | F10: Pilbara, Western Australia (East Pilbara Shire) | G10: -21.207 | H10: 119.308 | I10: Approximately 10 km | J10: Yes | L10: Paleoarchean rocks of the Pilbara Craton holding some of Earth's oldest stromatolites (Strelley Pool, c. 3.43 Ga) and c. 3.48 Ga hot-spring deposits (Dresser Formation). A key early-Earth and Mars biosignature analogue linked to Jezero crater studies. | M10: Early Earth | N10: Mars | O10: Habitability / biological | P10: Geological / geomorphological; Mineralogical; Geochemical | Q10: c. 3.43 Ga stromatolites of the Strelley Pool Chert (seven morphotypes on a peritidal carbonate platform); c. 3.48 Ga geyserite and hot-spring sinter of the Dresser Formation | R10: Strelley Pool stromatolites are among the strongest evidence for life c. 3.43 Ga, and their morphology and environmental context are used to argue for biogenicity. Dresser Formation geyserite with stromatolites and palisade fabric suggests life in terrestrial hot springs c. 3.48 Ga, which the authors present as an analogue for seeking fossil life in ancient Martian hot springs. The Mount Ada Basalt and Strelley Pool rocks have been compared with the olivine-carbonate unit at Jezero crater. | S10: Rocks have been silicified, metamorphosed and deformed over >3 billion years; biogenicity of some structures (e.g. small conical forms) is disputed; Earth's Archean surface chemistry and plate-tectonic setting differ from Mars. | T10: Ancient craton | U10: Chert; stromatolitic carbonate (dolomite); sandstone; conglomerate; breccia; geyserite (siliceous sinter); basalt; komatiitic basalt; felsic tuff | V10: Quartz; Dolomite; Calcite; Baryte; Pyrite; Galena; Hematite; Kaolinite; Illite; Anatase; Ankerite; Siderite | W10: Strelley Pool Chert c. 3.43 Ga (Paleoarchean); Dresser Formation c. 3.48 Ga | X10: Hot spring / hydrothermal | Y10: Hypersaline | AG10: Yes | AH10: Fossil microbial communities only (stromatolites, microbial mat fabrics, inferred EPS with gas bubbles); no living analogue biota studied | AI10: 3 | AJ10: Yes | AK10: Geological Survey of Western Australia (fieldwork permits cited by Duda et al. 2016); native title and pastoral-lease holders may also need to be consulted (unconfirmed) | AL10: Unknown | AM10: Marble Bar (Strelley Pool is c. 34 km W on Six Mile Creek) | AN10: Cooler months, June to August (mean daily maximum c. 27 °C at Marble Bar); avoid December–January (often >45 °C) and the December–March wet/cyclone season | AO10: Remote: Marble Bar is 152 km SE of Port Hedland, and Strelley Pool is c. 34 km W of Marble Bar. Road conditions and 4WD needs not confirmed from an official source. | AP10: Fieldwork has required permits from the Geological Survey of Western Australia; Duda et al. (2016) inspected the Trendall locality outcrop without sampling it. Strelley Pool is classified by the National Trust and listed as an indicative place on the Register of the National Estate. | AQ10: 3 | AR10: Extreme heat; Remoteness / no phone signal; Flash flood | AS10: Marble Bar holds the world record of 160 consecutive days at or above 37.8 °C, with a record high of 49.3 °C; cyclones can bring very heavy rain. Plan for heat, water and remote travel. | AV10: 46306 | AX10: Draft | AY10: Ratings are PROPOSALS by Claude: check against Rating scales, then fill rating_last_reviewed. geological_setting also: Hydrothermal / ore deposit Open issues: see Research log tab. | AZ10: =IF($B10="","",COUNTIF(References!$A$4:$A$503,$A10)) | BA10: =IF($B10="","",(LEN(A10)=0)+(LEN(B10)=0)+(LEN(D10)=0)+(LEN(G10)=0)+(LEN(H10)=0)+(LEN(I10)=0)+(LEN(J10)=0)+(LEN(L10)=0)+(LEN(M10)=0)+(LEN(O10)=0)+(LEN(R10)=0)+(LEN(X10)=0)+(LEN(AI10)=0)+(LEN(AJ10)=0)+(LEN(AQ10)=0)+(LEN(AR10)=0)+(LEN(AT10)=0)+(LEN(AU10)=0)+(LEN(AV10)=0)+(LEN(AX10)=0)) | BB10: =IF($B10="","",IF(AND(BA10=0,AZ10>=1),"Complete","Incomplete"))
A11: shark-bay-hamelin-pool-au | B11: Hamelin Pool Marine Nature Reserve, Shark Bay | C11: Hamelin Pool; Shark Bay stromatolites | D11: Australia | E11: AU | F11: Gascoyne, Western Australia (Shark Bay World Heritage Area) | G11: -26.44 | H11: 114.35 | I11: Region only | J11: Yes | K11: 1270 | L11: Hypersaline marine reserve in the Shark Bay World Heritage Area with the world's most diverse and abundant living marine stromatolites and microbial mats. A modern model for early-Earth microbial ecosystems and biosignatures. | M11: Early Earth | N11: Mars | O11: Habitability / biological | P11: Geochemical | Q11: Living marine stromatolites, microbialites and microbial mats (pustular, smooth and colloform mat types) | R11: Hamelin Pool's living stromatolites are modern counterparts of stromatolites found in the fossil record back to the Archean, so they serve as model systems for carbon cycling and microbial mat ecosystems. Metagenomics shows mats dominated by Proteobacteria and Cyanobacteria, with sulphate reducers and methanogens. | S11: Modern biota and an oxygenated atmosphere differ from Archean conditions; the sources opened do not discuss Mars directly, so the Mars link is indirect (via ancient stromatolite biosignatures). | T11: Sedimentary basin | U11: Microbial carbonate (stromatolites, microbialites); coquina (cockle-shell limestone) | X11: Hypersaline | AB11: 11 | AC11: 33 | AD11: About twice normal seawater; 54.5–56 ppt at Spaven Province sampling sites (April 2014), with 66–88 ppt reported across the pool | AG11: Yes | AH11: Cyanobacteria (Entophysalis, Dichothrix, Scytonema); Proteobacteria; Desulfovibrionales (sulphate reducers); methanogenic Euryarchaeota (Methanobacteriales); Thaumarchaeota | AI11: 2 | AJ11: Yes | AK11: Department of Biodiversity, Conservation and Attractions (DBCA), Western Australia (conditional licence for scientific access); Australian Government environment department for sample export/collection (cited in Babilonia et al. 2018) | AL11: Protected area / national park | AM11: Denham (c. 100 km NW); Overlander Roadhouse c. 35 km | AO11: 27 km from the North West Coastal Highway via Shark Bay Road; sealed except a short 2WD-suitable unsealed section to the car park. 750 m return walk from the car park to the stromatolites. | AP11: Scientific access requires a conditional licence from DBCA. Walking below the high-water mark is not permitted; no swimming, snorkelling, diving or boating over stromatolites or within 300 m of shore; no fishing. Stay on the boardwalk/viewing area. Boardwalk closed since Cyclone Seroja damage; view from the temporary fence. | AQ11: 2 | AR11: Remoteness / no phone signal | AS11: DBCA advises planning your visit and carrying a personal locator beacon (PLB). Drones must follow CASA rules; never enter the water to retrieve one. | AV11: 46306 | AX11: Draft | AY11: Ratings are PROPOSALS by Claude: check against Rating scales, then fill rating_last_reviewed. land_status also: UNESCO site; Indigenous or community land Open issues: see Research log tab. | AZ11: =IF($B11="","",COUNTIF(References!$A$4:$A$503,$A11)) | BA11: =IF($B11="","",(LEN(A11)=0)+(LEN(B11)=0)+(LEN(D11)=0)+(LEN(G11)=0)+(LEN(H11)=0)+(LEN(I11)=0)+(LEN(J11)=0)+(LEN(L11)=0)+(LEN(M11)=0)+(LEN(O11)=0)+(LEN(R11)=0)+(LEN(X11)=0)+(LEN(AI11)=0)+(LEN(AJ11)=0)+(LEN(AQ11)=0)+(LEN(AR11)=0)+(LEN(AT11)=0)+(LEN(AU11)=0)+(LEN(AV11)=0)+(LEN(AX11)=0)) | BB11: =IF($B11="","",IF(AND(BA11=0,AZ11>=1),"Complete","Incomplete"))
A12: arkaroola-au | B12: Arkaroola | C12: Arkaroola Wilderness Sanctuary; Arkaroola Protection Area; Mount Painter Inlier | D12: Australia | E12: AU | F12: Northern Flinders Ranges, South Australia | G12: -30.312 | H12: 139.336 | I12: Approximately 10 km | J12: No | K12: 610 | L12: A 610 km² wilderness sanctuary in the northern Flinders Ranges, chosen by Mars Society Australia as its main Mars analogue research area. It has Neoproterozoic sediments and stromatolites, fossil hydrothermal systems (Mount Gee) and radioactive hot springs nearby (Paralana). | M12: Mars | O12: Mineralogical | P12: Geological / geomorphological; Habitability / biological; Operational (instrument, rover or crew testing) | Q12: Fossil hydrothermal alteration and quartz-breccia systems in the Mount Painter Inlier (Mount Gee). Paralana radioactive hot springs with algal mats. Neoproterozoic stromatolites and ripple-laminated sandstones. | R12: Thomas & Walter (2002) used airborne and field short-wave infrared hyperspectral data to map hydrothermal alteration in the Mount Painter Inlier, as a test for characterising putative hydrothermal deposits on Mars. Mars Society Australia uses the area's varied rocks, regolith and duricrusts for remote-sensing, instrument and simulated-base testing. | T12: Hydrothermal / ore deposit | U12: Mesoproterozoic basement and uranium-bearing granite; quartz–hematite breccias; Wooltana Basalt; Neoproterozoic evaporitic, carbonate and clastic sediments (Callanna and Burra Groups); Sturtian tillites; stromatolites; iron, silica, carbonate and sulphate duricrusts | V12: Kaolinite; Muscovite; Biotite; K Feldspar; Halloysite; Quartz; Hematite | W12: Mesoproterozoic basement. Neoproterozoic sediments, including a stromatolite about 650 million years old. The main hydrothermal alteration is tentatively Permo-Carboniferous. Paralana springs are active today. | X12: Hot spring / hydrothermal | AC12: 80 | AF12: 640 | AG12: Yes | AH12: Algal mats on the floor of the Paralana hot springs in a high-radioactivity setting | AI12: 2 | AL12: Private | AO12: About 600–700 km north of Adelaide, roughly 8 hours by road. Charter flights are available from Adelaide airfields. The sanctuary offers guided 4WD tours (e.g. the Ridgetop tour) as well as self-drive tracks and bushwalking. | AQ12: 2 | AR12: Toxic gas | AS12: Radon (heavier than air) is emitted at the Paralana hot springs, so prolonged stays near the springs may be a health hazard. | AV12: 46306 | AX12: Draft | AY12: Ratings are PROPOSALS by Claude: check against Rating scales, then fill rating_last_reviewed. geological_setting also: Sedimentary basin land_status also: Protected area / national park Open issues: see Research log tab. | AZ12: =IF($B12="","",COUNTIF(References!$A$4:$A$503,$A12)) | BA12: =IF($B12="","",(LEN(A12)=0)+(LEN(B12)=0)+(LEN(D12)=0)+(LEN(G12)=0)+(LEN(H12)=0)+(LEN(I12)=0)+(LEN(J12)=0)+(LEN(L12)=0)+(LEN(M12)=0)+(LEN(O12)=0)+(LEN(R12)=0)+(LEN(X12)=0)+(LEN(AI12)=0)+(LEN(AJ12)=0)+(LEN(AQ12)=0)+(LEN(AR12)=0)+(LEN(AT12)=0)+(LEN(AU12)=0)+(LEN(AV12)=0)+(LEN(AX12)=0)) | BB12: =IF($B12="","",IF(AND(BA12=0,AZ12>=1),"Complete","Incomplete"))
A13: lanzarote-es | B13: Lanzarote | C13: Lanzarote and Chinijo Islands UNESCO Global Geopark; Timanfaya National Park | D13: Spain | E13: ES | F13: Canary Islands | G13: 29.039 | H13: -13.638 | I13: Region only | J13: No | K13: 886.85 | L13: Volcanic island in the Canary Islands with young lava fields (Timanfaya eruptions of 1730–1736 and 1824) and lava tubes. A Mars and Moon analogue used by ESA for PANGAEA astronaut geology training and for lava-tube astrobiology studies. | M13: Mars | N13: Moon | O13: Volcanic | P13: Operational (instrument, rover or crew testing); Habitability / biological | Q13: Martian and lunar volcanic terrains and lava tubes; interaction of volcanic activity and water | R13: Lanzarote has been described as one of the best terrestrial analogues for Martian volcanology, and its barren volcanic landscape is used by ESA to train astronauts in planetary field geology. Its lava tubes host secondary minerals and microbial communities whose biosignatures (e.g. Ca-rich fluorapatite precipitates) inform life-detection strategies for Martian caves. | T13: Volcanic | V13: Calcite; Fluorapatite; Gypsum; Halite; Opal | W13: Geological processes active for more than 15 Ma; historical eruptions 1730–1736 and 1824 (Timanfaya) | X13: Lava field / lava tube | Y13: Cave; Hot spring / hydrothermal | AF13: 671 | AG13: Yes | AH13: Crossiella; halophilic and halotolerant chemoorganotrophic bacteria (lava tubes); Salinisphaera; Alcanivorax; Alicyclobacillus (La Corona lava tube); lichens (Timanfaya) | AI13: 2 | AJ13: Varies | AK13: Timanfaya National Park direction (Parques Nacionales de Canarias); Lanzarote and Chinijo Islands UNESCO Global Geopark / Cabildo de Lanzarote | AL13: Protected area / national park | AM13: Arrecife; Yaiza; Tinajo | AO13: Timanfaya is reached by road (LZ-67 from Yaiza or Tinajo). Private vehicles may drive to Islote de Hilario (fee at the Taro gate); the Ruta de los Volcanes is only by Cabildo bus; guided walks (e.g. Termesana) must be booked in advance at the Mancha Blanca Visitor Centre. | AP13: In Timanfaya it is not permitted to walk or drive outside areas set up for public use (fragile lichens); plant collecting is prohibited; free independent access only on the coastal path; the Restricted Use Zone needs prior authorisation from the park direction; the Reserve Zone (over 90% of the park) is open only for scientific or management purposes. | AQ13: 2 | AR13: Extreme heat | AS13: Timanfaya has geothermal anomalies with surface temperatures above 100 °C; about 277 °C has been recorded at 10 cm depth at Islote de Hilario. Keep to designated areas. | AV13: 46306 | AX13: Draft | AY13: Ratings are PROPOSALS by Claude: check against Rating scales, then fill rating_last_reviewed. land_status also: UNESCO site Open issues: see Research log tab. | AZ13: =IF($B13="","",COUNTIF(References!$A$4:$A$503,$A13)) | BA13: =IF($B13="","",(LEN(A13)=0)+(LEN(B13)=0)+(LEN(D13)=0)+(LEN(G13)=0)+(LEN(H13)=0)+(LEN(I13)=0)+(LEN(J13)=0)+(LEN(L13)=0)+(LEN(M13)=0)+(LEN(O13)=0)+(LEN(R13)=0)+(LEN(X13)=0)+(LEN(AI13)=0)+(LEN(AJ13)=0)+(LEN(AQ13)=0)+(LEN(AR13)=0)+(LEN(AT13)=0)+(LEN(AU13)=0)+(LEN(AV13)=0)+(LEN(AX13)=0)) | BB13: =IF($B13="","",IF(AND(BA13=0,AZ13>=1),"Complete","Incomplete"))
A14: bockfjord-svalbard-sj | B14: Bockfjord Volcanic Complex | C14: Bockfjorden Volcanic Complex; Sverrefjell (Sverrefjellet); Sigurdfjell | D14: Norway (Svalbard) | E14: SJ | F14: Bockfjorden, Haakon VII Land, Spitsbergen, Svalbard | G14: 79.432 | H14: 13.305 | I14: Approximately 10 km | J14: Yes | L14: Quaternary basaltic volcanoes (Sverrefjell, Sigurdfjell) beside Bockfjorden, Svalbard. They contain carbonate globules like those in Martian meteorite ALH84001, with warm springs nearby. A long-running AMASE site for testing Mars instruments and astrobiology methods. | M14: Mars | O14: Mineralogical | P14: Geochemical; Volcanic; Habitability / biological; Operational (instrument, rover or crew testing) | Q14: Dolomite–magnesite carbonate globules in mantle xenoliths and lava vesicles; vent-hosted magnesite and carbonate-cemented lava breccias; Jotun and Troll warm springs | R14: Carbonate globules at Sverrefjell show carbonate and iron-oxide zoning similar to those in ALH84001, so they help test low-temperature hydrothermal and abiotic carbon-synthesis models for the meteorite. Breccia cements at Sverrefjell are an analogue for the Comanche carbonates at Gusev crater. AMASE has used the complex to test MSL and ExoMars instruments and contamination protocols. | T14: Volcanic | U14: Basalt; peridotite (mantle xenoliths); carbonate-cemented lava breccia | V14: Calcite; Dolomite; Magnesite; Huntite; Aragonite; Magnetite; Olivine; Allophane | W14: Sverrefjell and Sigurdfjell formed in subglacial eruptions c. 1 Ma (Amundsen et al. 2011). Wikipedia gives Sverrefjellet's formation as c. 2.6 Ma, with a last eruption between 6 ka and 1 Ma. | X14: Hot spring / hydrothermal | Y14: Glacial / subglacial | AC14: 25.6 | AF14: 507 | AI14: 4 | AJ14: Yes | AK14: Governor of Svalbard (Sysselmesteren) | AL14: Protected area / national park | AN14: Summer (AMASE fieldwork has been in August) | AP14: Register every project and fieldwork location in the Research in Svalbard (RiS) database. Apply by the fixed deadlines (15 Jan, 1 Mar, 1 Jul, 1 Oct); processing takes up to 8 weeks, and fieldwork must not start before the Governor replies. Fieldwork in national parks usually needs an exemption from the Governor. Loose stones need no permit in principle, but the area's protection rules still apply. Fossil collecting in protected areas needs an application. Terrain interventions larger than 20 × 20 cm need permission. Pre-1946 cultural monuments are protected, with a 100 m zone. Work under the Svalbard Environmental Protection Act. | AQ14: 4 | AR14: Dangerous wildlife | AS14: Polar bears: anyone outside settlements must carry suitable means of scaring off polar bears, and the Governor recommends a firearm. Campsites must be secured against bears, and camps that need an application must keep an awake, organised bear guard whenever people are present. Anyone travelling outside Management Area 10 must carry an emergency beacon registered with the Governor. Satellite phones cannot dial 112. | AV14: 46306 | AX14: Draft | AY14: Ratings are PROPOSALS by Claude: check against Rating scales, then fill rating_last_reviewed. Open issues: see Research log tab. | AZ14: =IF($B14="","",COUNTIF(References!$A$4:$A$503,$A14)) | BA14: =IF($B14="","",(LEN(A14)=0)+(LEN(B14)=0)+(LEN(D14)=0)+(LEN(G14)=0)+(LEN(H14)=0)+(LEN(I14)=0)+(LEN(J14)=0)+(LEN(L14)=0)+(LEN(M14)=0)+(LEN(O14)=0)+(LEN(R14)=0)+(LEN(X14)=0)+(LEN(AI14)=0)+(LEN(AJ14)=0)+(LEN(AQ14)=0)+(LEN(AR14)=0)+(LEN(AT14)=0)+(LEN(AU14)=0)+(LEN(AV14)=0)+(LEN(AX14)=0)) | BB14: =IF($B14="","",IF(AND(BA14=0,AZ14>=1),"Complete","Incomplete"))
A15: mauna-kea-us | B15: Mauna Kea | C15: Maunakea; Puʻu Hiwahine (2010 ISRU test site) | D15: United States | E15: US | F15: Hawaiʻi Island, Hawaii | G15: 19.821 | H15: -155.468 | I15: Approximately 10 km | J15: Yes | L15: Dormant shield volcano on Hawaiʻi Island whose fine-grained volcanic slopes hosted the 2010 and 2012 ILSO-ISRU field tests (PISCES, NASA, CSA, DLR, NORCAT) as a lunar and Mars analogue for instruments and resource extraction. | M15: Moon | N15: Mars | O15: Operational (instrument, rover or crew testing) | P15: Volcanic; Mineralogical | Q15: Fine-grained volcanic material and cinder-cone slopes (e.g. Puʻu Hiwahine, c. 2800 m) used for excavation, site preparation, mobility and ISRU instrument tests | R15: Mauna Kea hosted the 2010 ILSO-ISRU campaign, in which eight science teams tested and calibrated lunar in-situ instruments, and a 2012 follow-up under PISCES. Its fine-grained volcanic material is described as a suitable lunar and Martian analogue, and the site was proposed as a standard calibration location. | S15: An atmosphere, water and weathering make the material and conditions unlike the airless lunar surface; access and activities are limited by cultural, environmental and astronomical constraints. | T15: Volcanic | U15: Tholeiitic basalt; alkali basalt; hawaiite; mugearite; volcanic glass; gabbro | W15: Volcano c. 1 million years old; oldest dated rock c. 237,000 years (±31,000) | X15: High altitude / high UV | Y15: Lava field / lava tube | AE15: 2800 | AF15: 4207 | AI15: 3 | AK15: University of Hawaiʻi at Hilo Center for Maunakea Stewardship (formerly Office of Maunakea Management); Maunakea Stewardship and Oversight Authority (taking over management, transition from 1 July 2023) | AL15: Research station | AM15: Hilo | AO15: Saddle Road crosses the plateau between Mauna Kea and Mauna Loa. The summit road climbs nearly 5,000 ft over eight miles from the Visitor Information Station (2,804 m); it is unpaved, steep and requires dependable 4WD with low range above the VIS. No public fuel; arrive with at least half a tank. Summit open from 30 min before sunrise to 30 min after sunset. | AP15: Do not move, remove, collect or leave anything, including rocks. Rock piles may be cultural altars or markers protected by law. Stay on marked trails and roads; no off-road driving. Vehicles must be clean and free of invasive species. | AQ15: 4 | AR15: Altitude; Extreme cold; Remoteness / no phone signal | AS15: Acclimatise at least 30 minutes at the VIS (2,804 m) before going higher; descend immediately with altitude-illness symptoms. Children under 13, pregnant people, anyone who dived in the previous 24 hours or has heart, lung or blood-pressure conditions should not go above the VIS. Drink c. 500 ml per hour. Winter storms bring freezing temperatures, winds over 100 mph and white-outs. Intense UV. Mobile phones are for emergencies only; help may be hours away. | AV15: 46306 | AX15: Draft | AY15: Ratings are PROPOSALS by Claude: check against Rating scales, then fill rating_last_reviewed. Open issues: see Research log tab. | AZ15: =IF($B15="","",COUNTIF(References!$A$4:$A$503,$A15)) | BA15: =IF($B15="","",(LEN(A15)=0)+(LEN(B15)=0)+(LEN(D15)=0)+(LEN(G15)=0)+(LEN(H15)=0)+(LEN(I15)=0)+(LEN(J15)=0)+(LEN(L15)=0)+(LEN(M15)=0)+(LEN(O15)=0)+(LEN(R15)=0)+(LEN(X15)=0)+(LEN(AI15)=0)+(LEN(AJ15)=0)+(LEN(AQ15)=0)+(LEN(AR15)=0)+(LEN(AT15)=0)+(LEN(AU15)=0)+(LEN(AV15)=0)+(LEN(AX15)=0)) | BB15: =IF($B15="","",IF(AND(BA15=0,AZ15>=1),"Complete","Incomplete"))
A16: boulby-mine-gb | B16: Boulby Mine | C16: Boulby Underground Laboratory; Palmer Lab | D16: United Kingdom | E16: GB | F16: North Yorkshire, England | G16: 54.553 | H16: -0.825 | I16: Approximately 10 km | J16: No | L16: Working potash and polyhalite mine on the North Yorkshire coast hosting the STFC Boulby Underground Laboratory 1.1 km below ground in ~250-million-year-old Zechstein evaporites. Used for Mars-analogue instrument testing (MINAR) and deep subsurface brine habitability studies. | M16: Mars | O16: Operational (instrument, rover or crew testing) | P16: Habitability / biological; Mineralogical | Q16: Martian subsurface evaporites and brines | R16: The MINAR programme used Boulby's Permian evaporite sequence to test a planetary instrument suite (camera emulators, Raman, handheld XRD, drills) for characterising geological context and mineralogy at millimetre to metre scales. Subsurface brines in the mine show how ionic strength and water activity limit life, relevant to potentially habitable Martian brines. | S16: Active commercial mine with engineered roadways, air conditioning and human contamination; brines examined were not extreme in ionic strength. | T16: Evaporite basin | U16: Rock salt (halite); potash (sylvinite); polyhalite; dolomite; anhydrite; shale | V16: Halite; Sylvite; Polyhalite; Carnallite; Anhydrite; Dolomite | W16: Permian (Zechstein Sea evaporites, about 250 Ma) | X16: Evaporite | Y16: Hypersaline | Z16: 3.42 | AA16: 7.25 | AB16: 29.5 | AC16: 35.7 | AD16: Brine ionic strength 5.32–6.56 mol/L; Cl⁻ 159,347–209,639 mg/L; water activity 0.566–0.742 | AG16: Yes | AH16: Halobacteriales archaea (Haloarcula, Natronomonas, Halogeometricum, Halomicrobium, Halobacterium); Proteobacteria; Bacteroidetes; Firmicutes | AI16: 5 | AJ16: Yes | AK16: STFC Boulby Underground Laboratory (with ICL-UK, mine operator) | AL16: Research station | AM16: Loftus | AO16: Surface facilities lie just south-east of Boulby village, about 4.3 km east of Loftus, between Saltburn and Whitby. The laboratory is about 1,100 m underground in an operating mine. | AP16: Access only by arrangement with the Boulby Underground Laboratory (contact the lab to discuss facility access); no public access. | AQ16: 3 | AV16: 46306 | AX16: Draft | AY16: Ratings are PROPOSALS by Claude: check against Rating scales, then fill rating_last_reviewed. Open issues: see Research log tab. | AZ16: =IF($B16="","",COUNTIF(References!$A$4:$A$503,$A16)) | BA16: =IF($B16="","",(LEN(A16)=0)+(LEN(B16)=0)+(LEN(D16)=0)+(LEN(G16)=0)+(LEN(H16)=0)+(LEN(I16)=0)+(LEN(J16)=0)+(LEN(L16)=0)+(LEN(M16)=0)+(LEN(O16)=0)+(LEN(R16)=0)+(LEN(X16)=0)+(LEN(AI16)=0)+(LEN(AJ16)=0)+(LEN(AQ16)=0)+(LEN(AR16)=0)+(LEN(AT16)=0)+(LEN(AU16)=0)+(LEN(AV16)=0)+(LEN(AX16)=0)) | BB16: =IF($B16="","",IF(AND(BA16=0,AZ16>=1),"Complete","Incomplete"))
A17: lost-city-vent-field | B17: Lost City Hydrothermal Field | C17: Lost City; LCHF | D17: International waters (Mid-Atlantic Ridge) | F17: Southern wall of the Atlantis Massif, near the intersection of the Mid-Atlantic Ridge and the Atlantis Fracture Zone, North Atlantic (~30°N) | G17: 30.117 | H17: -42.117 | I17: Approximately 1 km | J17: No | L17: Off-axis, serpentinite-hosted vent field at 750–900 m depth on the Atlantis Massif with carbonate–brucite chimneys up to 60 m tall venting warm (40–90 °C), highly alkaline (pH 9–11), H2- and CH4-rich fluids. A leading analogue for icy-moon seafloor hydrothermal systems. | M17: Enceladus | N17: Europa; Icy moons (general) | O17: Habitability / biological | P17: Geochemical; Mineralogical | Q17: Carbonate–brucite chimneys venting alkaline hydrogen- and methane-rich fluids from serpentinisation of mantle peridotite | R17: Venting is driven by serpentinisation, reactions between seawater and mantle peridotite that need only olivine-bearing rock and water and produce H2 and CH4. Comparable systems could exist on the seafloors of ocean worlds such as Enceladus and Europa. Methane-cycling archaea in the chimney interiors show that such systems can support chemosynthetic life without magmatic heat. | S17: Lost City sits in oxygenated Earth seawater and hosts macrofauna and photosynthesis-derived organic input from above, unlike the oceans of icy moons. Its ocean chemistry, pressure and rock compositions differ from those inferred for Enceladus or Europa. | T17: Hydrothermal / ore deposit | U17: Serpentinised peridotite (serpentinite); carbonate chimney deposits | V17: Aragonite; Calcite; Brucite; Magnetite | W17: Hosted on ~1.5 Myr-old crust ~15 km from the spreading axis; venting for more than 120,000 years (radiocarbon dating of the oldest chimney deposits) | X17: Deep-sea vent | Y17: Alkaline; Hot spring / hydrothermal | Z17: 9 | AA17: 11 | AB17: 40 | AC17: 90 | AD17: Seawater-derived vent fluids | AE17: -900 | AF17: -750 | AG17: Yes | AH17: Methane-cycling archaea (Methanosarcinales-like, ANME-1) in warm porous chimney interiors; anaerobic thermophiles; Bacillota and Pseudomonadota bacteria; diverse macrofauna but without the high chemosynthetic biomass of black-smoker fields | AI17: 5 | AJ17: Varies | AL17: Unknown | AO17: Accessible only by ocean-going research vessel with remotely operated vehicles or crewed submersible (e.g. the 2005 NOAA expedition used ROVs Argus and Hercules from NOAA Ship Ronald H. Brown, with live video relayed to shore). Discovered in 2000. | AQ17: 3 | AR17: Sea or tides; Remoteness / no phone signal | AS17: Visitors work aboard a research vessel in the open North Atlantic far from land; all seafloor work is by ROV or submersible. | AV17: 46306 | AX17: Draft | AY17: Ratings are PROPOSALS by Claude: check against Rating scales, then fill rating_last_reviewed. Open issues: see Research log tab. | AZ17: =IF($B17="","",COUNTIF(References!$A$4:$A$503,$A17)) | BA17: =IF($B17="","",(LEN(A17)=0)+(LEN(B17)=0)+(LEN(D17)=0)+(LEN(G17)=0)+(LEN(H17)=0)+(LEN(I17)=0)+(LEN(J17)=0)+(LEN(L17)=0)+(LEN(M17)=0)+(LEN(O17)=0)+(LEN(R17)=0)+(LEN(X17)=0)+(LEN(AI17)=0)+(LEN(AJ17)=0)+(LEN(AQ17)=0)+(LEN(AR17)=0)+(LEN(AT17)=0)+(LEN(AU17)=0)+(LEN(AV17)=0)+(LEN(AX17)=0)) | BB17: =IF($B17="","",IF(AND(BA17=0,AZ17>=1),"Complete","Incomplete"))
A18: lake-vostok-aq | B18: Lake Vostok | C18: Subglacial Lake Vostok | D18: Antarctica | E18: AQ | F18: Beneath Vostok Station, central East Antarctic Ice Sheet | G18: -77.5 | H18: 106 | I18: Approximately 10 km | J18: Yes | K18: 12500 | L18: Antarctica's largest known subglacial lake (~250 × 50 km) under ~3.7–4 km of ice beneath Russia's Vostok Station. Accretion ice frozen from lake water contains microbes, making it a key analogue for ice-covered oceans on Europa and Enceladus. | M18: Europa | N18: Enceladus; Icy moons (general) | O18: Habitability / biological | P18: Cryospheric; Hydrological | Q18: Subglacial lake water and accretion ice refrozen onto the base of the ice sheet | R18: Lake Vostok is a liquid-water body sealed under kilometres of ice under high pressure (~350 atm), at about −3 °C and in permanent darkness, comparable to the ice-covered oceans of Europa and Enceladus. Microbes in accretion ice indicate the lake may support life that must rely on chemical energy, informing life-detection and clean-sampling strategies for icy moons. | S18: The lake water has not been sampled cleanly; all biological evidence so far comes from accretion ice or borehole-frozen water, and contamination by drilling fluid is disputed. Ice cover (~4 km) is much thinner than predicted for Europa's shell, and the lake is oxygenated from air hydrates in melting glacier ice. | T18: Glacial | W18: Lake sealed beneath ice c. 15 million years ago (estimates 15–25 Ma); overlying ice holds c. 400,000 years of climate record | X18: Glacial / subglacial | AB18: -3 | AC18: -3 | AD18: Freshwater (described as a deep freshwater lake at discovery) | AF18: 3488 | AG18: Unknown | AH18: Accretion-ice microbes at 2.8 × 10^3–3.6 × 10^4 cells/mL related to alpha- and beta-Proteobacteria and Actinomycetes; viable Gram-negative bacteria; thermophile-related sequences such as Hydrogenophilus thermoluteolus; unknown bacterial phylotypes (AF532061, w123-10). Life in the lake water itself is unconfirmed. | AI18: 5 | AJ18: Yes | AK18: Competent national authority of the expedition's Antarctic Treaty Party (e.g. UK: FCDO Polar Regions Department); station access only through the Arctic and Antarctic Research Institute (Russia) | AL18: Research station | AM18: Vostok Station (Russia), above the lake | AO18: Only reachable through Vostok Station (78.465°S, 106.837°E; 3,488 m), a year-round Russian station administered by the Arctic and Antarctic Research Institute, historically supplied from Mirny Station; has a skiway. The lake surface lies ~4,000 m below the ice surface and was first reached by borehole on 6 February 2012. | AP18: Lake access only by deep borehole drilling. Clean-room facilities and a contaminant library are considered prerequisites for microbiological work; drilling stopped ~100 m above the lake in 1998 to avoid contamination. Antarctic Treaty permits required. | AQ18: 5 | AR18: Extreme cold; Altitude; Remoteness / no phone signal | AS18: Vostok Station holds the record low air temperature of −89.2 °C (mean annual about −55 °C). At 3,488 m, low oxygen causes headaches and nosebleeds and acclimatisation can take one to eight weeks. Extremely isolated, with about 30 staff in summer and 15 in winter. | AV18: 46306 | AX18: Draft | AY18: Ratings are PROPOSALS by Claude: check against Rating scales, then fill rating_last_reviewed. Open issues: see Research log tab. | AZ18: =IF($B18="","",COUNTIF(References!$A$4:$A$503,$A18)) | BA18: =IF($B18="","",(LEN(A18)=0)+(LEN(B18)=0)+(LEN(D18)=0)+(LEN(G18)=0)+(LEN(H18)=0)+(LEN(I18)=0)+(LEN(J18)=0)+(LEN(L18)=0)+(LEN(M18)=0)+(LEN(O18)=0)+(LEN(R18)=0)+(LEN(X18)=0)+(LEN(AI18)=0)+(LEN(AJ18)=0)+(LEN(AQ18)=0)+(LEN(AR18)=0)+(LEN(AT18)=0)+(LEN(AU18)=0)+(LEN(AV18)=0)+(LEN(AX18)=0)) | BB18: =IF($B18="","",IF(AND(BA18=0,AZ18>=1),"Complete","Incomplete"))
A19: lava-beds-us | B19: Lava Beds National Monument | D19: United States | E19: US | F19: Modoc and Siskiyou Counties, California (northern flank of Medicine Lake volcano) | G19: 41.71 | H19: -121.51 | I19: Approximately 10 km | J19: No | K19: 189 | L19: More than 780 basaltic lava tube caves; used to test how lunar lava tubes could be detected and how stable they are | M19: Moon | N19: Mars | O19: Geological / geomorphological | P19: Operational (instrument, rover or crew testing); Habitability / biological | Q19: Lunar lava tubes and skylights | R19: Basaltic lava tubes with skylights and roof collapses resembling lunar tubes. Used to model magnetic anomalies for mapping lunar tubes from the surface (Bell et al. 2022) and to test lunar tube stability models with measured geometry and rock strength (Theinat et al. 2019). NASA BRAILLE also uses the caves as a Mars astrobiology analogue. | S19: Terrestrial tubes are much smaller (~30 m) than proposed lunar tubes; Earth has an atmosphere and weathering. | T19: Volcanic | U19: Basalt | X19: Lava field / lava tube | Y19: Cave | AB19: 10 | AC19: 13 | AG19: Yes | AH19: Bats, including possible maternity colonies | AI19: 2 | AJ19: Yes | AK19: Free caving permit from the Visitor Center (white-nose syndrome prevention). Research permits: contact the monument. https://www.nps.gov/labe/planyourvisit/caving.htm | AL19: Protected area / national park | AM19: Tulelake, California (services also in Tionesta, CA and Merrill, OR, c. 20–30 min from the Visitor Center) | AN19: Late spring to autumn: summer highs average 24–27 °C (75–80 °F); the Medicine Lake Road approach is open only mid-June to October and some southern roads may close November to mid-May. Snow is possible in any month; the monument and campground are open all year. | AO19: No public transport. About 1 hour from Klamath Falls, OR via OR 39, CA 161 and Hill Road; 1.5–2 hours from Weed, CA. Nearest airport Medford, OR (c. 2 hours). No fuel in the park; fill up in Klamath Falls, Merrill, Tulelake or Alturas. Limited mobile signal (some at the Visitor Center, which has WiFi). Winter: icy roads; FS 97, FS 49 and FS 10 may close. | AP19: Do not break formations or mark walls; ask the monument about research sampling permits. | AQ19: 3 | AR19: Unstable ground | AS19: Low ceilings, uneven footing, steep stairs and drop-offs from collapsed tubes; risk of disorientation in complex caves. Wear a helmet, carry several lights, never go alone. Some caves closed; check the current list. | AV19: 46306 | AX19: Draft | AY19: Coordinates approximate (monument area, ~189 km²). Ratings are PROPOSALS by Claude: check against Rating scales, then fill rating_last_reviewed. Open issues: see Research log tab. | AZ19: =IF($B19="","",COUNTIF(References!$A$4:$A$503,$A19)) | BA19: =IF($B19="","",(LEN(A19)=0)+(LEN(B19)=0)+(LEN(D19)=0)+(LEN(G19)=0)+(LEN(H19)=0)+(LEN(I19)=0)+(LEN(J19)=0)+(LEN(L19)=0)+(LEN(M19)=0)+(LEN(O19)=0)+(LEN(R19)=0)+(LEN(X19)=0)+(LEN(AI19)=0)+(LEN(AJ19)=0)+(LEN(AQ19)=0)+(LEN(AR19)=0)+(LEN(AT19)=0)+(LEN(AU19)=0)+(LEN(AV19)=0)+(LEN(AX19)=0)) | BB19: =IF($B19="","",IF(AND(BA19=0,AZ19>=1),"Complete","Incomplete"))
AZ20: =IF($B20="","",COUNTIF(References!$A$4:$A$503,$A20)) | BA20: =IF($B20="","",(LEN(A20)=0)+(LEN(B20)=0)+(LEN(D20)=0)+(LEN(G20)=0)+(LEN(H20)=0)+(LEN(I20)=0)+(LEN(J20)=0)+(LEN(L20)=0)+(LEN(M20)=0)+(LEN(O20)=0)+(LEN(R20)=0)+(LEN(X20)=0)+(LEN(AI20)=0)+(LEN(AJ20)=0)+(LEN(AQ20)=0)+(LEN(AR20)=0)+(LEN(AT20)=0)+(LEN(AU20)=0)+(LEN(AV20)=0)+(LEN(AX20)=0)) | BB20: =IF($B20="","",IF(AND(BA20=0,AZ20>=1),"Complete","Incomplete"))
AZ21: =IF($B21="","",COUNTIF(References!$A$4:$A$503,$A21)) | BA21: =IF($B21="","",(LEN(A21)=0)+(LEN(B21)=0)+(LEN(D21)=0)+(LEN(G21)=0)+(LEN(H21)=0)+(LEN(I21)=0)+(LEN(J21)=0)+(LEN(L21)=0)+(LEN(M21)=0)+(LEN(O21)=0)+(LEN(R21)=0)+(LEN(X21)=0)+(LEN(AI21)=0)+(LEN(AJ21)=0)+(LEN(AQ21)=0)+(LEN(AR21)=0)+(LEN(AT21)=0)+(LEN(AU21)=0)+(LEN(AV21)=0)+(LEN(AX21)=0)) | BB21: =IF($B21="","",IF(AND(BA21=0,AZ21>=1),"Complete","Incomplete"))
AZ22: =IF($B22="","",COUNTIF(References!$A$4:$A$503,$A22)) | BA22: =IF($B22="","",(LEN(A22)=0)+(LEN(B22)=0)+(LEN(D22)=0)+(LEN(G22)=0)+(LEN(H22)=0)+(LEN(I22)=0)+(LEN(J22)=0)+(LEN(L22)=0)+(LEN(M22)=0)+(LEN(O22)=0)+(LEN(R22)=0)+(LEN(X22)=0)+(LEN(AI22)=0)+(LEN(AJ22)=0)+(LEN(AQ22)=0)+(LEN(AR22)=0)+(LEN(AT22)=0)+(LEN(AU22)=0)+(LEN(AV22)=0)+(LEN(AX22)=0)) | BB22: =IF($B22="","",IF(AND(BA22=0,AZ22>=1),"Complete","Incomplete"))
AZ23: =IF($B23="","",COUNTIF(References!$A$4:$A$503,$A23)) | BA23: =IF($B23="","",(LEN(A23)=0)+(LEN(B23)=0)+(LEN(D23)=0)+(LEN(G23)=0)+(LEN(H23)=0)+(LEN(I23)=0)+(LEN(J23)=0)+(LEN(L23)=0)+(LEN(M23)=0)+(LEN(O23)=0)+(LEN(R23)=0)+(LEN(X23)=0)+(LEN(AI23)=0)+(LEN(AJ23)=0)+(LEN(AQ23)=0)+(LEN(AR23)=0)+(LEN(AT23)=0)+(LEN(AU23)=0)+(LEN(AV23)=0)+(LEN(AX23)=0)) | BB23: =IF($B23="","",IF(AND(BA23=0,AZ23>=1),"Complete","Incomplete"))
AZ24: =IF($B24="","",COUNTIF(References!$A$4:$A$503,$A24)) | BA24: =IF($B24="","",(LEN(A24)=0)+(LEN(B24)=0)+(LEN(D24)=0)+(LEN(G24)=0)+(LEN(H24)=0)+(LEN(I24)=0)+(LEN(J24)=0)+(LEN(L24)=0)+(LEN(M24)=0)+(LEN(O24)=0)+(LEN(R24)=0)+(LEN(X24)=0)+(LEN(AI24)=0)+(LEN(AJ24)=0)+(LEN(AQ24)=0)+(LEN(AR24)=0)+(LEN(AT24)=0)+(LEN(AU24)=0)+(LEN(AV24)=0)+(LEN(AX24)=0)) | BB24: =IF($B24="","",IF(AND(BA24=0,AZ24>=1),"Complete","Incomplete"))
AZ25: =IF($B25="","",COUNTIF(References!$A$4:$A$503,$A25)) | BA25: =IF($B25="","",(LEN(A25)=0)+(LEN(B25)=0)+(LEN(D25)=0)+(LEN(G25)=0)+(LEN(H25)=0)+(LEN(I25)=0)+(LEN(J25)=0)+(LEN(L25)=0)+(LEN(M25)=0)+(LEN(O25)=0)+(LEN(R25)=0)+(LEN(X25)=0)+(LEN(AI25)=0)+(LEN(AJ25)=0)+(LEN(AQ25)=0)+(LEN(AR25)=0)+(LEN(AT25)=0)+(LEN(AU25)=0)+(LEN(AV25)=0)+(LEN(AX25)=0)) | BB25: =IF($B25="","",IF(AND(BA25=0,AZ25>=1),"Complete","Incomplete"))
AZ26: =IF($B26="","",COUNTIF(References!$A$4:$A$503,$A26)) | BA26: =IF($B26="","",(LEN(A26)=0)+(LEN(B26)=0)+(LEN(D26)=0)+(LEN(G26)=0)+(LEN(H26)=0)+(LEN(I26)=0)+(LEN(J26)=0)+(LEN(L26)=0)+(LEN(M26)=0)+(LEN(O26)=0)+(LEN(R26)=0)+(LEN(X26)=0)+(LEN(AI26)=0)+(LEN(AJ26)=0)+(LEN(AQ26)=0)+(LEN(AR26)=0)+(LEN(AT26)=0)+(LEN(AU26)=0)+(LEN(AV26)=0)+(LEN(AX26)=0)) | BB26: =IF($B26="","",IF(AND(BA26=0,AZ26>=1),"Complete","Incomplete"))
AZ27: =IF($B27="","",COUNTIF(References!$A$4:$A$503,$A27)) | BA27: =IF($B27="","",(LEN(A27)=0)+(LEN(B27)=0)+(LEN(D27)=0)+(LEN(G27)=0)+(LEN(H27)=0)+(LEN(I27)=0)+(LEN(J27)=0)+(LEN(L27)=0)+(LEN(M27)=0)+(LEN(O27)=0)+(LEN(R27)=0)+(LEN(X27)=0)+(LEN(AI27)=0)+(LEN(AJ27)=0)+(LEN(AQ27)=0)+(LEN(AR27)=0)+(LEN(AT27)=0)+(LEN(AU27)=0)+(LEN(AV27)=0)+(LEN(AX27)=0)) | BB27: =IF($B27="","",IF(AND(BA27=0,AZ27>=1),"Complete","Incomplete"))
AZ28: =IF($B28="","",COUNTIF(References!$A$4:$A$503,$A28)) | BA28: =IF($B28="","",(LEN(A28)=0)+(LEN(B28)=0)+(LEN(D28)=0)+(LEN(G28)=0)+(LEN(H28)=0)+(LEN(I28)=0)+(LEN(J28)=0)+(LEN(L28)=0)+(LEN(M28)=0)+(LEN(O28)=0)+(LEN(R28)=0)+(LEN(X28)=0)+(LEN(AI28)=0)+(LEN(AJ28)=0)+(LEN(AQ28)=0)+(LEN(AR28)=0)+(LEN(AT28)=0)+(LEN(AU28)=0)+(LEN(AV28)=0)+(LEN(AX28)=0)) | BB28: =IF($B28="","",IF(AND(BA28=0,AZ28>=1),"Complete","Incomplete"))
AZ29: =IF($B29="","",COUNTIF(References!$A$4:$A$503,$A29)) | BA29: =IF($B29="","",(LEN(A29)=0)+(LEN(B29)=0)+(LEN(D29)=0)+(LEN(G29)=0)+(LEN(H29)=0)+(LEN(I29)=0)+(LEN(J29)=0)+(LEN(L29)=0)+(LEN(M29)=0)+(LEN(O29)=0)+(LEN(R29)=0)+(LEN(X29)=0)+(LEN(AI29)=0)+(LEN(AJ29)=0)+(LEN(AQ29)=0)+(LEN(AR29)=0)+(LEN(AT29)=0)+(LEN(AU29)=0)+(LEN(AV29)=0)+(LEN(AX29)=0)) | BB29: =IF($B29="","",IF(AND(BA29=0,AZ29>=1),"Complete","Incomplete"))
AZ30: =IF($B30="","",COUNTIF(References!$A$4:$A$503,$A30)) | BA30: =IF($B30="","",(LEN(A30)=0)+(LEN(B30)=0)+(LEN(D30)=0)+(LEN(G30)=0)+(LEN(H30)=0)+(LEN(I30)=0)+(LEN(J30)=0)+(LEN(L30)=0)+(LEN(M30)=0)+(LEN(O30)=0)+(LEN(R30)=0)+(LEN(X30)=0)+(LEN(AI30)=0)+(LEN(AJ30)=0)+(LEN(AQ30)=0)+(LEN(AR30)=0)+(LEN(AT30)=0)+(LEN(AU30)=0)+(LEN(AV30)=0)+(LEN(AX30)=0)) | BB30: =IF($B30="","",IF(AND(BA30=0,AZ30>=1),"Complete","Incomplete"))
AZ31: =IF($B31="","",COUNTIF(References!$A$4:$A$503,$A31)) | BA31: =IF($B31="","",(LEN(A31)=0)+(LEN(B31)=0)+(LEN(D31)=0)+(LEN(G31)=0)+(LEN(H31)=0)+(LEN(I31)=0)+(LEN(J31)=0)+(LEN(L31)=0)+(LEN(M31)=0)+(LEN(O31)=0)+(LEN(R31)=0)+(LEN(X31)=0)+(LEN(AI31)=0)+(LEN(AJ31)=0)+(LEN(AQ31)=0)+(LEN(AR31)=0)+(LEN(AT31)=0)+(LEN(AU31)=0)+(LEN(AV31)=0)+(LEN(AX31)=0)) | BB31: =IF($B31="","",IF(AND(BA31=0,AZ31>=1),"Complete","Incomplete"))
... AZ503: =IF($B503="","",COUNTIF(References!$A$4:$A$503,$A503)) | BA503: =IF($B503="","",(LEN(A503)=0)+(LEN(B503)=0)+(LEN(D503)=0)+(LEN(G503)=0)+(LEN(H503)=0)+(LEN(I503)=0)+(LEN(J503)=0)+(LEN(L503)=0)+(LEN(M503)=0)+(LEN(O503)=0)+(LEN(R503)=0)+(LEN(X503)=0)+(LEN(AI503)=0)+(LEN(AJ503)=0)+(LEN(AQ503)=0)+(LEN(AR503)=0)+(LEN(AT503)=0)+(LEN(AU503)=0)+(LEN(AV503)=0)+(LEN(AX503)=0)) | BB503: =IF($B503="","",IF(AND(BA503=0,AZ503>=1),"Complete","Incomplete"))

Sheet References
A1: REFERENCES: one row per source. Every number on the Sites tab should trace to a row here.
A2: site_id | B2: citation | C2: doi_or_url | D2: fields_supported | E2: added_by | F2: notes
A3: Must match an id on the Sites tab | B3: Author(s), year, title, journal | C3: DOI preferred, e.g. 10.1089/ast.2013.1234 | D3: Which fields this source backs up; separate with ; | E3: Your name
A4: rio-tinto-es | B4: Amils, R., Fernández-Remolar, D. & the IPBSL Team (2014). Río Tinto: A Geochemical and Mineralogical Terrestrial Analogue of Mars. Life, 4(3), 511–534. | C4: 10.3390/life4030511 | D4: summary; analogue_for_primary; analogue_type_primary; analogue_type_other; target_feature; science_relevance; analogue_limitations; geological_setting; rock_types; key_minerals; age; environment_type_primary; environment_type_other; biology_present; notable_organisms; nearest_town; hazards; safety_notes | F4: Peer-reviewed. Opened on MDPI. Review: 92 km river, mean pH 2.3, mineralogy (jarosite, schwertmannite, goethite, hematite etc.), terrace/gossan ages, microbiology, Meridiani comparison and analogue limitations. No water temperature given.
A5: rio-tinto-es | B5: Gómez, F., Walter, N., Amils, R., Rull, F., Klingelhöfer, A.K., Kviderova, J., Sarrazin, P., Foing, B., Behar, A., Fleischer, I., Parro, V., Garcia-Villadangos, M., Blake, D., Martin Ramos, J.D., Direito, S., Mahapatra, P., Stam, C., Venkateswaran, K. & Voytek, M. (2011). Multidisciplinary integrated field campaign to an acidic Martian Earth analogue with astrobiological interest: Rio Tinto. International Journal of Astrobiology, 10(3), 291–305. | C5: 10.1017/S147355041100005X | D5: analogue_for_primary; analogue_type_primary; analogue_type_other; target_feature; science_relevance; geological_setting; rock_types; environment_type_other; biology_present | F5: Peer-reviewed. Opened on Cambridge Core. CAREX field campaign; Iberian Pyritic Belt; jarosite and iron oxides vs Meridiani; endolithic phototrophs in acidic salt deposits.
A6: rio-tinto-es | B6: Junta de Andalucía (2005). Decreto 558/2004, de 14 de diciembre, por el que se declara el Paisaje Protegido de Río Tinto. BOJA no. 10, 17 January 2005. | C6: https://www.juntadeandalucia.es/boja/2005/10/2 | D6: region; extent_km2; access_level; permits_required; permit_authority; land_status; nearest_town; sampling_rules | F6: Official source. Official decree: 16,956.79 ha across 11 municipalities incl. Minas de Riotinto and Nerva; access and activity rules (Art. 4).
A7: rio-tinto-es | B7: Wikipedia contributors. Rio Tinto (river). Wikipedia. | C7: https://en.wikipedia.org/wiki/Rio_Tinto_(river) | D7: alt_names; country_code; region; latitude; longitude; coordinate_precision; summary; analogue_for_other; ph_min; ph_max; hazards; safety_notes | F7: Secondary source. Source coordinates (37.21 N, 6.938 W); pH 2–2.5 in most areas; mining history (from c. 3000 BC; copper production restarted 2016); Mars and possible Europa analogue statements.
A8: atacama-yungay-cl | B8: Navarro-González, R., Rainey, F. A., Molina, P., Bagaley, D. R., Hollen, B. J., de la Rosa, J., Small, A. M., Quinn, R. C., Grunthaner, F. J., Cáceres, L., Gómez-Silva, B. & McKay, C. P. (2003). Mars-like soils in the Atacama Desert, Chile, and the dry limit of microbial life. Science, 302(5647), 1018–1021. | C8: 10.1126/science.1089143 | D8: summary; analogue_for_primary; analogue_type_primary; analogue_type_other; target_feature; science_relevance; environment_type_primary; biology_present | F8: Peer-reviewed. Verified via the Crossref API record and the ANID (Chile) investigator database. doi.org was rate-limited and could not be opened. Founding Yungay Mars-soil analogue paper: trace organics, no DNA recovered, very low culturable bacteria, non-biological oxidation of organics.
A9: atacama-yungay-cl | B9: Azua-Bustos, A., Fairén, A. G., González-Silva, C., Ascaso, C., Carrizo, D., Fernández-Martínez, M. Á., Fernández-Sampedro, M., García-Descalzo, L., García-Villadangos, M., Martin-Redondo, M. P., Sánchez-García, L., Wierzchos, J. & Parro, V. (2018). Unprecedented rains decimate surface microbial communities in the hyperarid core of the Atacama Desert. Scientific Reports, 8, 16706. | C9: 10.1038/s41598-018-35051-w | D9: region; summary; analogue_for_primary; analogue_type_other; target_feature; science_relevance; environment_type_primary; environment_type_other; salinity; key_minerals; biology_present; notable_organisms | F9: Peer-reviewed. Opened on nature.com. Covers Yungay-area soils (nitrates, sulphates, perchlorates, halite and sodium nitrate), 2015 and 2017 rain events (core mean annual precipitation mostly below 4 mm), post-rain microbiology, and Mars nitrogen-cycle and flooding analogue arguments.
A10: atacama-yungay-cl | B10: PANGAEA dataset (2021). Soil temperature and relative humidity measurements in 70 cm soil depth at the Yungay hyperarid site in 2017. | C10: 10.1594/PANGAEA.929562 | D10: alt_names; region; latitude; longitude; coordinate_precision | F10: Secondary source. Opened the B2FIND metadata record. Gives the site location as lat -24.100, lon -70.010. Used for coordinates only.
A11: dallol-et | B11: Belilla, J., Moreira, D., Jardillier, L., Reboul, G., Benzerara, K., López-García, J. M., Bertolino, P., López-Archilla, A. I. & López-García, P. (2019). Hyperdiverse archaea near life limits at the polyextreme geothermal Dallol area. Nature Ecology & Evolution, 3(11), 1552–1561. | C11: 10.1038/s41559-019-1005-0 | D11: analogue_type_other; science_relevance; environment_type_other; salinity; biology_present; notable_organisms | F11: Peer-reviewed. Opened on nature.com and confirmed via Crossref. Identifies chaotropic Mg/Ca brines and pH around 0 with NaCl saturation as barriers to life. Ultrasmall archaea dominate where life occurs. Mentions a 110 °C hydrocarbon-rich chimney at 'Little Dallol'.
A12: dallol-et | B12: Kotopoulou, E., Delgado Huertas, A., García-Ruiz, J. M., Domínguez-Vera, J. M., López-García, J. M., Guerra-Tschuschke, I. & Rull, F. (2019). A polyextreme hydrothermal system controlled by iron: the case of Dallol at the Afar Triangle. ACS Earth and Space Chemistry, 3(1), 90–99. | C12: 10.1021/acsearthspacechem.8b00141 | D12: alt_names; region; summary; analogue_for_primary; analogue_for_other; analogue_type_primary; analogue_type_other; target_feature; science_relevance; geological_setting; rock_types; key_minerals; environment_type_primary; environment_type_other; ph_min; ph_max; temp_min_c; temp_max_c; salinity; altitude_min_m; altitude_max_m; hazard_rating; hazards; safety_notes | F12: Peer-reviewed. Confirmed via Crossref (online 6 December 2018, print 17 January 2019). Full text read from the Universidad de Granada repository (digibug.ugr.es). Spring pH 0.16 to -0.5, pools down to -1.7, Black Lake about 2.5, Yellow Lake about 1.7. Springs 105.6–108.4 °C, pools cooling to about 32 °C. Iron up to 150 g/L. Dome about 60 m below sea level; depression about 120 m below sea level. Lists the minerals and describes Dallol as a Martian analogue site.
A13: dallol-et | B13: UK Foreign, Commonwealth & Development Office (2026). Ethiopia travel advice: summary, safety and security, and regional risks (updated 7 October 2026). | C13: https://www.gov.uk/foreign-travel-advice/ethiopia/regional-risks | D13: hazard_rating; hazards; safety_notes; access_level | F13: Official source. Afar: advice against all travel within 20 km of Eritrea and within 50 km of Tigray, and all but essential travel to the rest. Renewed clashes in parts of Afar. Foreign nationals cannot travel to Afar airports. Medical facilities outside the capital are extremely limited. Does NOT mention Dallol, Danakil, guides, escorts, gas or heat.
A14: dallol-et | B14: Wikipedia contributors. Dallol (hydrothermal system). Wikipedia (accessed 11 October 2026). | C14: https://en.wikipedia.org/wiki/Dallol_(hydrothermal_system) | D14: alt_names; region; latitude; longitude; geological_setting; rock_types; key_minerals; age; biology_present; notable_organisms; hazard_rating; hazards; safety_notes | F14: Secondary source. Coordinates 14°14′30″N 40°18′00″E. 1926 phreatic eruptions; January 2011 activity. Gas composition (CO2, H2S, N2, SO2). Notes on 'acid basins, toxic fumes' and 'unbearable heat'. Summarises the 2019 life and no-life studies.
A15: mcmurdo-dry-valleys-aq | B15: Friedmann, E. I. (1982). Endolithic microorganisms in the Antarctic cold desert. Science, 215(4536), 1045–1053. | C15: 10.1126/science.215.4536.1045 | D15: summary; analogue_type_primary; target_feature; science_relevance; biology_present; notable_organisms | F15: Peer-reviewed. Founding paper on the cryptoendolithic lichen/microbial communities of the Dry Valleys. Title, author, year and pages checked against Crossref and Europe PMC records; abstract read.
... A99: lava-beds-us | B99: National Park Service. NPS Geodiversity Atlas: Lava Beds National Monument, California. | C99: https://www.nps.gov/articles/nps-geodiversity-atlas-lava-beds-national-monument-california.htm | D99: extent_km2; region | F99: Area 18,896 ha (46,692 acres)

Sheet Photos
A1: PHOTOS: one row per photo. Image files live in assets/photos/ on the website. Only public domain, CC0, CC BY or CC BY-SA images.
A2: site_id | B2: file | C2: caption | D2: author | E2: licence | F2: licence_url | G2: source_page
A3: rio-tinto-es | B3: rio-tinto-es-1.jpg | C3: Red acidic Río Tinto seen from the mining railway | D3: Gzzz | E3: CC BY-SA 4.0 | F3: https://creativecommons.org/licenses/by-sa/4.0/ | G3: https://commons.wikimedia.org/wiki/File:R%C3%ADo_Tinto_7.jpg
A4: rio-tinto-es | B4: rio-tinto-es-2.jpg | C4: Bright red waters at the Río Tinto source, Nerva | D4: LBM1948 | E4: CC BY-SA 4.0 | F4: https://creativecommons.org/licenses/by-sa/4.0/ | G4: https://commons.wikimedia.org/wiki/File:R%C3%ADo_Tinto%2C_nacimiento_05.jpg
A5: rio-tinto-es | B5: rio-tinto-es-3.jpg | C5: Río Tinto riverbed near Los Frailes station, Zalamea la Real | D5: LBM1948 | E5: CC BY-SA 4.0 | F5: https://creativecommons.org/licenses/by-sa/4.0/ | G5: https://commons.wikimedia.org/wiki/File:R%C3%ADo_Tinto%2C_Los_Frailes_11.jpg
A6: atacama-yungay-cl | B6: atacama-yungay-cl-1.jpg | C6: Barren hyperarid Atacama plain between Antofagasta and Taltal | D6: Valerio Pillar | E6: CC BY-SA 2.0 | F6: https://creativecommons.org/licenses/by-sa/2.0/ | G6: https://commons.wikimedia.org/wiki/File:Atacama_Desert_between_Antofagasta_and_Taltal.jpg
A7: atacama-yungay-cl | B7: atacama-yungay-cl-2.jpg | C7: Typical hyperarid Atacama landscape near Calama, Antofagasta Region | D7: Diego Delso | E7: CC BY-SA 4.0 | F7: https://creativecommons.org/licenses/by-sa/4.0/ | G7: https://commons.wikimedia.org/wiki/File:Paisaje_cerca_de_Calama%2C_Chile%2C_2016-02-01%2C_DD_83.JPG
A8: dallol-et | B8: dallol-et-1.jpg | C8: Aerial view of the Dallol hydrothermal field | D8: Thomas Fuhrmann | E8: CC BY-SA 4.0 | F8: https://creativecommons.org/licenses/by-sa/4.0/ | G8: https://commons.wikimedia.org/wiki/File:Ethiopia_-_Dallol.jpg
A9: dallol-et | B9: dallol-et-2.jpg | C9: Acid pool with salt, sulfur and mineral crusts at Dallol | D9: Hervé Sthioul | E9: CC BY 2.5 | F9: https://creativecommons.org/licenses/by/2.5/ | G9: https://commons.wikimedia.org/wiki/File:Dallol-2001.jpg
A10: dallol-et | B10: dallol-et-3.jpg | C10: Salt geyser formation at Dallol | D10: Jan Markiewicz | E10: CC BY-SA 3.0 | F10: https://creativecommons.org/licenses/by-sa/3.0/ | G10: https://commons.wikimedia.org/wiki/File:Dallol_gejzer_solny_-_panoramio.jpg
A11: mcmurdo-dry-valleys-aq | B11: mcmurdo-dry-valleys-aq-1.jpg | C11: Wright Valley looking west from Bull Pass towards Lake Vanda | D11: David Saul | E11: Public domain | G11: https://commons.wikimedia.org/wiki/File:Wright_Valley_From_Bull_Pass.jpg
A12: mcmurdo-dry-valleys-aq | B12: mcmurdo-dry-valleys-aq-2.jpg | C12: Blood Falls seeping from Taylor Glacier into Lake Bonney | D12: National Science Foundation/Peter Rejcek | E12: Public domain | G12: https://commons.wikimedia.org/wiki/File:Blood_Falls_by_Peter_Rejcek.jpg
A13: mcmurdo-dry-valleys-aq | B13: mcmurdo-dry-valleys-aq-3.jpg | C13: Taylor Valley with Canada Glacier and Lake Hoare | D13: David Haney, NSF | E13: Public domain | G13: https://commons.wikimedia.org/wiki/File:Taylor_Valley_2008_01.jpg
A14: haughton-crater-ca | B14: haughton-crater-ca-1.jpg | C14: View near the edge of Haughton impact crater | D14: Haughton Mars Project | E14: Public domain | G14: https://commons.wikimedia.org/wiki/File:Edge_of_Haughton_Crater_%282672692755%29.jpg
A15: haughton-crater-ca | B15: haughton-crater-ca-2.jpg | C15: Rock formation inside Haughton Crater, Devon Island | D15: Haughton Mars Project | E15: Public domain | G15: https://commons.wikimedia.org/wiki/File:Rock_Formation_in_Haughton_Crater_%282673474042%29.jpg
A16: haughton-crater-ca | B16: haughton-crater-ca-3.jpg | C16: NASA K10 rovers near the Haughton-Mars Project base camp | D16: NASA | E16: Public domain | G16: https://commons.wikimedia.org/wiki/File:Rovers_Red_and_Black_at_Houghton_Crater_Devon_Island_Canada.jpg
A17: iceland-volcanic-fields-is | B17: iceland-volcanic-fields-is-1.jpg | C17: Holuhraun fissure eruption, September 2014 | D17: Robert Askew ( https://imaggeo.egu.eu/user/283721/ ) | E17: CC BY-SA 3.0 | F17: https://creativecommons.org/licenses/by-sa/3.0/ | G17: https://commons.wikimedia.org/wiki/File:Holuhraun_Fissure_Eruption_in_Iceland_-_September_2014.jpg
A18: iceland-volcanic-fields-is | B18: iceland-volcanic-fields-is-2.jpg | C18: Aerial view of the Holuhraun eruption and lava field | D18: Milan Nykodym from Kutna Hora, Czech Republic | E18: CC BY-SA 2.0 | F18: https://creativecommons.org/licenses/by-sa/2.0/ | G18: https://commons.wikimedia.org/wiki/File:B%C3%A1r%C3%B0arbunga_-_Holuhraun_%2814971302084%29.jpg
A19: iceland-volcanic-fields-is | B19: iceland-volcanic-fields-is-3.jpg | C19: Leirhnjúkur lava field in the Krafla caldera | D19: rheins | E19: CC BY 3.0 | F19: https://creativecommons.org/licenses/by/3.0/ | G19: https://commons.wikimedia.org/wiki/File:Leirhnj%C3%BAkur_Lava_Field_-_2013.08_-_panoramio.jpg
A20: pilbara-strelley-pool-au | B20: pilbara-strelley-pool-au-1.jpg | C20: Archean pillow basalt outcrop, Mount Ada Basalt, eastern Pilbara | D20: A.R. Brenner, R.R. Fu, A.J. Brown, E.B. Hodgin, D.T. Flannery & M.D. Schmitz | E20: CC BY 4.0 | F20: https://creativecommons.org/licenses/by/4.0/ | G20: https://commons.wikimedia.org/wiki/File:Pillow_structures_in_Mount_Ada_Basalt.jpg
A21: pilbara-strelley-pool-au | B21: pilbara-strelley-pool-au-2.jpg | C21: Hamersley Range landscape, Pilbara Region | D21: Barry T Coles at English Wikipedia | E21: Public domain | G21: https://commons.wikimedia.org/wiki/File:Hamersley_Range%2C_Pilbara_Region%2C_Western_Australia.JPG
A22: shark-bay-hamelin-pool-au | B22: shark-bay-hamelin-pool-au-1.jpg | C22: Living stromatolites in Hamelin Pool, Shark Bay | D22: Paul Harrison | E22: CC BY-SA 3.0 | F22: https://creativecommons.org/licenses/by-sa/3.0/ | G22: https://commons.wikimedia.org/wiki/File:Stromatolites_in_Sharkbay.jpg
A23: shark-bay-hamelin-pool-au | B23: shark-bay-hamelin-pool-au-2.jpg | C23: Stromatolites at Hamelin Pool Marine Nature Reserve | D23: Martin Kraft | E23: CC BY-SA 3.0 | F23: https://creativecommons.org/licenses/by-sa/3.0/ | G23: https://commons.wikimedia.org/wiki/File:MK-08233_Hamelin_Pool_Stromatolites.jpg
A24: shark-bay-hamelin-pool-au | B24: shark-bay-hamelin-pool-au-3.jpg | C24: Stromatolite field in shallow water at Hamelin Pool | D24: Phil Whitehouse from London, United Kingdom | E24: CC BY 2.0 | F24: https://creativecommons.org/licenses/by/2.0/ | G24: https://commons.wikimedia.org/wiki/File:Hamelin_Pool_%28Stromatolites%29_%282052468336%29.jpg
A25: arkaroola-au | B25: arkaroola-au-1.jpg | C25: Sunset over the Arkaroola ranges, northern Flinders Ranges | D25: John Morton from Adelaide | E25: CC BY 2.0 | F25: https://creativecommons.org/licenses/by/2.0/ | G25: https://commons.wikimedia.org/wiki/File:Arkaroola_Sunset%2C_South_Australia_%2849849951657%29.jpg
A26: arkaroola-au | B26: arkaroola-au-2.jpg | C26: Former Radium Ridge uranium mine at Mount Gee, Arkaroola | D26: Geomartin | E26: CC BY-SA 3.0 | F26: https://creativecommons.org/licenses/by-sa/3.0/ | G26: https://commons.wikimedia.org/wiki/File:Radiumridgemine_arkaroola.JPG
A27: arkaroola-au | B27: arkaroola-au-3.jpg | C27: Flinders Ranges at Paralana Hot Springs | D27: State Government Photographer | E27: CC0 | F27: https://creativecommons.org/publicdomain/zero/1.0/ | G27: https://commons.wikimedia.org/wiki/File:View_of_Flinders_Ranges%28GN10237%29.jpg
A28: lanzarote-es | B28: lanzarote-es-1.jpg | C28: ʻAʻā lava field in Timanfaya National Park | D28: H. Zell | E28: CC BY-SA 3.0 | F28: https://creativecommons.org/licenses/by-sa/3.0/ | G28: https://commons.wikimedia.org/wiki/File:Timanfaya_-_Lanzarote_04.jpg
A29: lanzarote-es | B29: lanzarote-es-2.jpg | C29: Pāhoehoe lava field in Timanfaya National Park | D29: H. Zell | E29: CC BY-SA 3.0 | F29: https://creativecommons.org/licenses/by-sa/3.0/ | G29: https://commons.wikimedia.org/wiki/File:Timanfaya_-_Lanzarote_02.jpg
A30: lanzarote-es | B30: lanzarote-es-3.jpg | C30: Lava fields and volcanic cones, Timanfaya National Park | D30: Gerd Eichmann | E30: CC BY 4.0 | F30: https://creativecommons.org/licenses/by/4.0/ | G30: https://commons.wikimedia.org/wiki/File:Lanzarote-Nationalpark_Timanfaya-12-Lava-2015-gje.jpg
A31: bockfjord-svalbard-sj | B31: bockfjord-svalbard-sj-1.jpg | C31: Bockfjorden with Sverrefjellet volcano and Adolfbreen glacier | D31: Bjoertvedt | E31: CC BY-SA 3.0 | F31: https://creativecommons.org/licenses/by-sa/3.0/ | G31: https://commons.wikimedia.org/wiki/File:Haakon_VII_Land_Bockfjorden_IMG_5543_Trolltindane_Sverrefjellet_Adolfbreen_Sm%C3%B6rstabben.JPG
A32: bockfjord-svalbard-sj | B32: bockfjord-svalbard-sj-2.jpg | C32: Sverrefjellet and surrounding peaks above Bockfjorden, Svalbard | D32: Bjoertvedt | E32: CC BY-SA 3.0 | F32: https://creativecommons.org/licenses/by-sa/3.0/ | G32: https://commons.wikimedia.org/wiki/File:Haakon_VII_Land_Sverrefjellet_Trolltindane_Adolfbreen_Williamstaarnet_behind_Roosflya_IMG_5500.JPG
A33: mauna-kea-us | B33: mauna-kea-us-1.jpg | C33: Cinder cones (puʻu) at the summit of Mauna Kea | D33: S P Schmidt | E33: CC BY 4.0 | F33: https://creativecommons.org/licenses/by/4.0/ | G33: https://commons.wikimedia.org/wiki/File:Pu%27u_on_Mauna_Kea.jpg
... A38: boulby-mine-gb | B38: boulby-mine-gb-3.jpg | C38: View across farmland towards Boulby Potash Mine | D38: Michael Jagger | E38: CC BY-SA 2.0 | F38: https://creativecommons.org/licenses/by-sa/2.0/ | G38: https://commons.wikimedia.org/wiki/File:View_towards_Boulby_Potash_Mine_-_geograph.org.uk_-_1752884.jpg
A39: lost-city-vent-field | B39: lost-city-vent-field-1.jpg | C39: Tall carbonate chimney at the Lost City field | D39: National Science Foundation (University of Washington/Woods Hole Oceanographic Institution) | E39: Public domain | G39: https://commons.wikimedia.org/wiki/File:Lost_City_%28hydrothermal_field%2900.jpg
A40: lost-city-vent-field | B40: lost-city-vent-field-2.jpg | C40: Carbonate tower rising at the Lost City vent field | D40: “Susan Lang, U. of SC. / NSF / ROV Jason / 2018 © Woods Hole Oceanographic Institution.” | E40: CC BY-SA 4.0 | F40: https://creativecommons.org/licenses/by-sa/4.0/ | G40: https://commons.wikimedia.org/wiki/File:Sulis_20180919080019.jpg
A41: lost-city-vent-field | B41: lost-city-vent-field-3.jpg | C41: Carbonate formation at Lost City, Okeanos Explorer expedition | D41: NOAA | E41: Public domain | G41: https://commons.wikimedia.org/wiki/File:Formation_at_Lost_City_Field.jpg
A42: lake-vostok-aq | B42: lake-vostok-aq-1.jpg | C42: Russian Vostok Station on the East Antarctic plateau | D42: NSF/Josh Landis, employee 1999-2001 | E42: Public domain | G42: https://commons.wikimedia.org/wiki/File:Russian_station_Vostok.jpg
A43: lake-vostok-aq | B43: lake-vostok-aq-2.jpg | C43: RADARSAT radar image of the ice surface above Lake Vostok | D43: NASA/Goddard Space Flight Center Scientific Visualization Studio. Additional credit goes to Canadian Space Agency, RADARSAT International Inc. | E43: Public domain | G43: https://commons.wikimedia.org/wiki/File:Lake_Vostok_NASA.jpg
A44: lava-beds-us | B44: lava-beds-us-1.jpg | C44: Illuminated lava tube cave at Lava Beds National Monument | D44: Leonard G. | E44: Public domain | G44: https://commons.wikimedia.org/wiki/File:IlluminatedLavaTubeAtLBNMi-C0070.JPG
A45: lava-beds-us | B45: lava-beds-us-2.jpg | C45: Classic lava tube passage, Lava Beds National Monument | D45: Dave Bunnell | E45: CC BY-SA 3.0 | F45: https://creativecommons.org/licenses/by-sa/3.0/ | G45: https://commons.wikimedia.org/wiki/File:Classic_lava_tube_passage.jpg
A46: lava-beds-us | B46: lava-beds-us-3.jpg | C46: Valentine Cave lava tube, Lava Beds National Monument | D46: Dave Bunnell / Under Earth Images | E46: CC BY-SA 2.5 | F46: https://creativecommons.org/licenses/by-sa/2.5/ | G46: https://commons.wikimedia.org/wiki/File:Valentine_Cave.JPG

Sheet Comparisons
A1: COMPARISONS: the area on the target body shown beside each site. Longitude is east-positive (-180 to 180). view_km sets how wide an area the map shows at first.
A2: site_id | B2: body | C2: area_name | D2: latitude | E2: longitude | F2: view_km | G2: why_compared | H2: confidence | I2: pairing_source_title | J2: pairing_source_url | K2: coordinate_source_title | L2: coordinate_source_url | M2: notes
A3: rio-tinto-es | B3: Mars | C3: Meridiani Planum – Eagle crater (Opportunity landing site) | D3: -1.95 | E3: -5.53 | F3: 300 | G3: Rio Tinto's acidic, iron-sulfate waters precipitate jarosite and hematite. Opportunity found the same pairing in the sulfate-rich outcrops and hematite 'blueberries' at Meridiani Planum. | H3: high | I3: Fernández-Remolar et al. 2005, The Rio Tinto Basin, Spain: Mineralogy, Sedimentary Geobiology, and Implications for Interpretation of Outcrop Rocks at Meridiani Planum, Mars (EPSL 240) – NTRS | J3: https://ntrs.nasa.gov/citations/20080026258 | K3: Eagle (crater) – Wikipedia | L3: https://en.wikipedia.org/wiki/Eagle_(crater) | M3: Wikipedia gives 1.95°S 354.47°E; 354.47−360 = −5.53.
A4: atacama-yungay-cl | B4: Mars | C4: Chryse Planitia – Viking 1 lander site | D4: 22.697 | E4: -47.95 | F4: 300 | G4: In 2003, McKay and Navarro-González's team repeated the Viking life-detection experiments in Yungay soils. They got Viking-like null results, with trace organics broken down by non-biological oxidants. Yungay soils also contain perchlorate. | H4: high | I4: Mars-like Atacama Desert Could Explain Viking No-Life Results – Mars Daily (on Navarro-González et al. 2003, Science) | J4: https://www.marsdaily.com/reports/MarsLike_Atacama_Desert_Could_Explain_Viking_No_Life_Results.html | K4: Viking 1 – Wikipedia | L4: https://en.wikipedia.org/wiki/Viking_1 | M4: Planetocentric 22.697°N 312.05°E (312.05−360 = −47.95). Wikipedia also gives planetographic 22.480°N 47.967°W. I chose Viking over Phoenix because the Yungay study replicated Viking directly; Phoenix is the alternative for perchlorate. Viking 2 (Utopia Planitia) would serve equally well.
A5: dallol-et | B5: Mars | C5: Gale crater – Vera Rubin ridge (Curiosity) | D5: -5.4 | E5: 137.8 | F5: 160 | G5: Dallol's hyper-acidic, chloride- and iron-rich fluids precipitate jarosite and akaganeite together. Curiosity's CheMin found that rare pairing in Vera Rubin ridge mudstones, attributed to very acidic (pH ~1.4–2), saline diagenetic fluids. | H5: medium | I5: Kotopoulou et al. 2019, A Polyextreme Hydrothermal System Controlled by Iron: The Case of Dallol at the Afar Triangle (ACS Earth Space Chem.) – full text | J5: https://digibug.ugr.es/bitstream/handle/10481/59480/acsearthspacechem.8b00141.pdf?sequence=1 | K5: Gale (crater) – Wikipedia | L5: https://en.wikipedia.org/wiki/Gale_(crater) | M5: Gale crater centre (5.4°S 137.8°E). Bradbury Landing is at 4.5°S 137.4°E. No sourced point coordinate for Vera Rubin ridge was found. Kotopoulou et al. 2019 and Cavalazzi et al. 2019 call Dallol a Mars analogue but name no specific Mars locality, so this pairing is inferred from the matching minerals. Meridiani Planum (jarosite) is a plausible alternative.
A6: mcmurdo-dry-valleys-aq | B6: Mars | C6: Vastitas Borealis – 'Green Valley', Phoenix lander site | D6: 68.2188 | E6: -125.7492 | F6: 100 | G6: Like the Phoenix site, the high-elevation Dry Valleys (e.g. University Valley) have ice-cemented ground beneath dry permafrost. Heldmann et al. call them the closest Earth analogue for martian ground ice. | H6: high | I6: Heldmann et al., Mars: Periglacial Morphology and Implications for Future Landing Sites – NTRS | J6: https://ntrs.nasa.gov/citations/20150023012 | K6: Phoenix (spacecraft) – Wikipedia | L6: https://en.wikipedia.org/wiki/Phoenix_(spacecraft) | M6: Wikipedia infobox: 68.2188°N 125.7492°W (= 234.25°E).
A7: haughton-crater-ca | B7: Mars | C7: Ius Chasma tributary valleys (western Valles Marineris) | D7: -8.3 | E7: -84.6 | F7: 200 | G7: Devon Island's canyons near Haughton have been described as morphologic counterparts of the broad, winding V-shaped tributary valleys of Ius Chasma in western Valles Marineris. | H7: medium | I7: Haughton Crater (Lakdawalla, The Planetary Society) | J7: https://www.planetary.org/articles/haughton_crater | K7: PIA09371: Ius Chasma Tributary Valleys and Adjacent Plains – NASA/JPL (PDS Rings mirror) | L7: https://pds-rings.seti.org/press_releases/pages/PIA09xxx/PIA09371.html | M7: Centre of HiRISE image PIA09371 of the Ius Chasma tributaries: −8.3°, 275.4°E (275.4−360 = −84.6). Ius Chasma as a whole is at 7°S 85.8°W (Wikipedia).
A8: iceland-volcanic-fields-is | B8: Mars | C8: Central Elysium Planitia – lava-flooded crater (young flood basalts) | D8: -1 | E8: -160 | F8: 300 | G8: The 2014–2015 Holuhraun fissure eruption is used as an analogue for young fissure-fed flood lavas in Elysium Planitia. Both share rubbly and inflated flows, polygonal terrain and extensional fissures. | H8: high | I8: Voigt et al. 2025, The 2014–2015 Holuhraun lava flow-field in Iceland as a planetary analog for young volcanic terrains in Elysium Planitia, Mars (PSJ 6:81) – USGS Pubs | J8: https://pubs.usgs.gov/publication/70275623 | K8: Flood Basalts on Mars and Iceland – NASA Earth Observatory | L8: https://science.nasa.gov/earth/earth-observatory/flood-basalts-on-mars-and-iceland-92858/ | M8: NASA Earth Observatory: the crater is 'centered at 1°S, 160°W' (west → −160 east-positive). Alternative representative point: Athabasca Valles flood lava, 8.6°N 205.0°W = 155.0°E (Wikipedia), where Icelandic rootless-cone comparisons (Mývatn) are also made.
A9: pilbara-strelley-pool-au | B9: Mars | C9: Jezero crater (delta–lake system, Perseverance) | D9: 18.38 | E9: 77.58 | F9: 60 | G9: NASA and partner teams studied the 3.35 Ga Strelley Pool stromatolites in the Pilbara to learn how to recognise ancient biosignatures in the lake and delta deposits Perseverance is exploring in Jezero crater. | H9: high | I9: NASA Partners Study Ancient Life in Australia to Inform Mars Search – NASA JPL | J9: https://www.jpl.nasa.gov/news/nasa-partners-study-ancient-life-in-australia-to-inform-mars-search/ | K9: Jezero (crater) – Wikipedia | L9: https://en.wikipedia.org/wiki/Jezero_(crater) | M9: 18°23′N 77°35′E (Wikipedia).
A10: shark-bay-hamelin-pool-au | B10: Mars | C10: Jezero crater – western delta front and marginal carbonates ('bathtub ring') | D10: 18.4446 | E10: 77.4509 | F10: 20 | G10: Hamelin Pool's living stromatolites form along a shoreline. Jezero's carbonates line its ancient lakeshore in a 'bathtub ring' that NASA flags as a prime spot to look for stromatolite-like structures. | H10: low | I10: NASA's Mars 2020 Will Hunt for Microscopic Fossils – NASA | J10: https://www.nasa.gov/solar-system/nasas-mars-2020-will-hunt-for-microscopic-fossils/ | K10: Perseverance (rover) – Wikipedia | L10: https://en.wikipedia.org/wiki/Perseverance_(rover) | M10: Perseverance touchdown point 18.4446°N 77.4509°E (Wikipedia), just east of the western delta front. No sourced point coordinate for the marginal carbonate unit was found. No source found names Shark Bay and Jezero together, so this pairing is inferred.
A11: arkaroola-au | B11: Mars | C11: Gusev crater – Home Plate, Columbia Hills (opaline silica) | D11: -14.6 | E11: 175.5 | F11: 10 | G11: Arkaroola's Mount Painter / Mount Gee hydrothermal systems preserve silica–hematite deposits. Home Plate is Mars's best-known hydrothermal silica site: nearly pure opaline silica, interpreted as an extinct fumarole or hot-spring deposit. | H11: low | I11: Thomas et al. 2012, The Flinders Ranges and surrounds, South Australia: a window on astrobiology and planetary geology (UNSW ACA) | J11: https://unsw.edu.au/content/dam/pdfs/science/aca/research-reports/2022-01-aca-research/2022-01-Thomas%2c%20Clarke%2c%20Gostin%2c%20Williams%20and%20Walter%20%202012.pdf | K11: Home Plate (Mars) – Wikipedia | L11: https://en.wikipedia.org/wiki/Home_Plate_(Mars) | M11: 14°36′S 175°30′E (Wikipedia). The Arkaroola literature found calls the area a Mars analogue only in general terms. Thomas et al. 2012 cites Nili Patera (hydrothermal silica) only in a reference title. This pairing is therefore inferred; Nili Patera is the main alternative.
A12: lanzarote-es | B12: Mars | C12: Nephentes–Amenthes cone field (hydrovolcanic tuff rings/cones, southern Utopia margin) | D12: 16.62 | E12: 103.33 | F12: 100 | G12: Brož & Hauber (2013) compared the Nephentes–Amenthes cones with Lanzarote's Caldera Blanca tuff ring. They found 'obvious' morphological and topographic similarities and used them to argue for phreatomagmatic eruptions on Mars. | H12: medium | I12: Brož & Hauber 2013 (JGR Planets) – Table 3.2 and Fig. 3.10 compare with Caldera Blanca, Lanzarote | J12: https://www.ig.cas.cz/wp-content/uploads/2018/10/broz_and_hauber_2013_phreatomagmatic.pdf | K12: Brož & Hauber 2013, Hydrovolcanic tuff rings and cones as indicators for phreatomagmatic explosive eruptions on Mars (JGR Planets 118) | L12: https://www.ig.cas.cz/wp-content/uploads/2018/10/broz_and_hauber_2013_phreatomagmatic.pdf | M12: Example cone 'at 16.62°N/103.33°E' quoted in Brož & Hauber 2013 (east longitude). The Lanzarote Geopark's 'Lanzarote Marte en la Tierra' booklet cites this work for Caldera Blanca.
A13: bockfjord-svalbard-sj | B13: Mars | C13: Gusev crater – Comanche carbonate outcrop, Columbia Hills | D13: -14.6 | E13: 175.5 | F13: 10 | G13: Amundsen et al. (2011) state that the carbonate cements in Sverrefjell breccias are an analogue to the Comanche carbonates in Gusev crater. Comanche holds about 25 wt% Mg-Fe carbonate, which Spirit found in the Columbia Hills. | H13: medium | I13: Amundsen et al. 2011, Cryogenic Origin for Mars Analog Carbonates in the Bockfjord Volcanic Complex Svalbard (LPSC 42) – NTRS | J13: https://ntrs.nasa.gov/citations/20110008112 | K13: Home Plate (Mars) – Wikipedia | L13: https://en.wikipedia.org/wiki/Home_Plate_(Mars) | M13: No published point coordinate for Comanche was found. This is the Home Plate / Columbia Hills reference point (14.6°S 175.5°E). Comanche lies in the Columbia Hills in the same southward view from Husband Hill (PIA17760), within roughly a kilometre (not verified).
A14: mauna-kea-us | B14: Moon | C14: Lunar south pole – Shackleton crater (permanently shadowed ISRU target) | D14: -89.67 | E14: 129.78 | F14: 300 | G14: NASA's 2010 RESOLVE field demonstration on Mauna Kea tested volatile prospecting and extraction in lunar-like volcanic tephra. The system was designed to go to permanently shadowed craters at the lunar poles, and Shackleton is the classic example. | H14: medium | I14: Captain et al., RESOLVE's Field Demonstration on Mauna Kea, Hawaii 2010 – NTRS | J14: https://ntrs.nasa.gov/citations/20100033667 | K14: Shackleton (crater) – Wikipedia | L14: https://en.wikipedia.org/wiki/Shackleton_(crater) | M14: 89°40′S 129°47′E (Wikipedia). The RESOLVE abstract names polar permanently shadowed craters generally, not Shackleton specifically.
... A18: lava-beds-us | B18: Moon | C18: Marius Hills hole (lava-tube skylight), Oceanus Procellarum | D18: 14.2 | E18: -56.7 | F18: 200 | G18: NASA teams have tested lava-tube exploration methods in Lava Beds' caves for the Moon. The Marius Hills hole is the first-identified lunar skylight into a probable lava tube: about 65 m wide and 80–88 m deep. | H18: medium | I18: Are Moon Caves Safe for Astronauts? Earth's Lava Tubes Can Help Us Find Out – Space.com | J18: https://space.com/41921-exploring-lava-tubes-for-moon-landings.html | K18: Marius Hills hole (Lakdawalla, The Planetary Society, 2009) | L18: https://www.planetary.org/articles/2173 | M18: 303.3°E, 14.2°N (Haruyama et al. 2009 via The Planetary Society); 303.3−360 = −56.7. The sources compare Lava Beds with lunar lava tubes in general, not with Marius Hills specifically.

Sheet Research log
A1: Research log: what was checked, what still needs checking, and why each rating was proposed
A3: site_id | B3: type | C3: detail | D3: done?
A4: rio-tinto-es | B4: Rating rationale: hazard_rating | C4: 2 Low: the main hazards are contact with pH ~2 water and old/active mine ground; manageable with basic precautions (gloves, eye protection, keeping out of mine areas).
A5: rio-tinto-es | B5: Rating rationale: access_level | C5: 2 Easy: road access to the river and mining towns; public land open via designated access points under the protected-landscape decree; mine areas and restricted zones need permission.
A6: rio-tinto-es | B6: Open issue | C6: No opened source gives water temperature; temp_min_c/temp_max_c left null.
A7: rio-tinto-es | B7: Open issue | C7: pH range 2.0–2.5 is from Wikipedia only; the peer-reviewed source (r1) gives a mean of 2.3 and calls it constant. Replace with a primary measured range if one is found.
A8: rio-tinto-es | B8: Open issue | C8: Could not open the Fernández-Remolar et al. (2005) EPSL paper (10.1016/j.epsl.2005.09.010): doi.org and Crossref were rate-limited and the CSIC repository blocked access, so it is not cited.
A9: rio-tinto-es | B9: Open issue | C9: Europa as a secondary analogue is from Wikipedia, which flags the claim as needing a better source; drop it unless a peer-reviewed source is found.
A10: rio-tinto-es | B10: Open issue | C10: extent_km2 is the area of the Paisaje Protegido (169.57 km²), not the whole catchment.
A11: rio-tinto-es | B11: Open issue | C11: Coordinates are the river source (Peña de Hierro area); the river is 92–100 km long, so precision is set to approximately 10 km.
A12: rio-tinto-es | B12: Open issue | C12: Best season, transport and altitude not found in an opened source.
A13: rio-tinto-es | B13: Judgement-based fields | C13: coordinate_precision, sensitive_site, access_level, hazard_rating
A14: atacama-yungay-cl | B14: Rating rationale: hazard_rating | C14: Proposed 2 (Low): a hyperarid desert with heat, sun and dryness exposure. None of the opened sources describes a specific hazard, so this is judgement only.
A15: atacama-yungay-cl | B15: Rating rationale: access_level | C15: Proposed 2 (Easy): unconfirmed. No official access or permit source was found. The owner should check road access and land tenure.
... A155: lava-beds-us | B155: Judgement-based fields | C155: best_season, sensitive_site, hazard_rating, access_level

Sheet Rating scales
A1: Rating scales
A2: Rate the highest hazard a normal visitor meets, not the worst case anywhere. Ratings are guidance, not a risk assessment. Re-check every 3 years.
A4: Level | B4: Hazard rating | C4: Access level
A5: 1 | B5: Minimal: like a normal day out; standard fieldwork kit | C5: Open: roadside or public path, no permit
A6: 2 | B6: Low: some exposure (heat, uneven ground); basic precautions | C6: Easy: road access; permit simple or not needed
A7: 3 | B7: Moderate: real hazards; needs a group, a plan and suitable kit | C7: Planned: 4x4, hike or boat, or a permit that takes weeks
A8: 4 | B8: High: serious hazards (toxic gas, altitude, extreme cold); experienced leaders or a guide | C8: Expedition: remote, multi-day, local guide or authority escort
A9: 5 | B9: Extreme: life-threatening without specialist training and equipment | C9: Restricted: research station, military, or invitation only

Sheet Vocabularies
A1: analogue_for | B1: analogue_type | C1: environment_type | D1: geological_setting | E1: hazards | F1: land_status | G1: coordinate_precision | H1: review_status | I1: yes_no | J1: yes_no_varies | K1: yes_no_unknown | L1: level_1_5
A2: Mars | B2: Geological / geomorphological | C2: Hyperarid | D2: Volcanic | E2: Extreme heat | F2: Public | G2: Exact | H2: Draft | I2: Yes | J2: Yes | K2: Yes | L2: 1
A3: Moon | B3: Mineralogical | C3: Polar desert | D3: Impact | E3: Extreme cold | F3: Protected area / national park | G3: Approximately 1 km | H3: In review | I3: No | J3: No | K3: No | L3: 2
A4: Venus | B4: Geochemical | C4: Permafrost | D4: Sedimentary basin | E4: Altitude | F4: UNESCO site | G4: Approximately 10 km | H4: Verified | J4: Varies | K4: Unknown | L4: 3
A5: Mercury | B5: Habitability / biological | C5: Glacial / subglacial | D5: Evaporite basin | E5: Toxic gas | F5: Private | G5: Region only | H5: Needs update | L5: 4
A6: Europa | B6: Impact | C6: Hot spring / hydrothermal | D6: Hydrothermal / ore deposit | E6: Acidic or caustic water | F6: Indigenous or community land | L6: 5
A7: Enceladus | B7: Volcanic | C7: Deep-sea vent | D7: Glacial | E7: Unstable ground | F7: Military
A8: Titan | B8: Cryospheric | C8: Acidic | D8: Aeolian | E8: Rockfall | F8: Research station
A9: Ganymede | B9: Aeolian | C9: Alkaline | D9: Ancient craton | E9: Volcanic activity | F9: Unknown
A10: Callisto | B10: Hydrological | C10: Hypersaline | E10: Flash flood
A11: Io | B11: Operational (instrument, rover or crew testing) | C11: Evaporite | E11: Remoteness / no phone signal
A12: Ceres | C12: Iron-rich | E12: Dangerous wildlife
A13: Vesta | C13: Sulphur-rich | E13: Old mine workings
A14: Comets | C14: Lava field / lava tube | E14: Political instability
A15: Asteroids (general) | C15: Impact structure | E15: Sea or tides
A16: Icy moons (general) | C16: High altitude / high UV
A17: Exoplanets (general) | C17: Cave
A18: Early Earth
A20: Maintainers only: add new values at the bottom of a list, then extend that list's dropdown range on the Sites sheet. Values in "_other" columns and the hazards column are separated by semicolons and must match these lists.
